{
  "hooks": [
    {
      "hookId": "伏笔-洞穴深处阴影",
      "startChapter": 39,
      "type": "伏笔",
      "status": "open",
      "lastAdvancedChapter": 39,
      "expectedPayoff": "待展开",
      "notes": "从深处拐角渗出/比匣内活物大得多"
    },
    {
      "hookId": "伏笔-滴答声",
      "startChapter": 0,
      "type": "open",
      "status": "open",
      "lastAdvancedChapter": 0,
      "expectedPayoff": "洞穴深处威胁逼近（呼吸声+湿润蠕动）→与63章呼应",
      "notes": ""
    },
    {
      "hookId": "伏笔-阿纱的秘密",
      "startChapter": 0,
      "type": "open",
      "status": "open",
      "lastAdvancedChapter": 0,
      "expectedPayoff": "欲言又止/眼圈红/知道两年前女人下落→未说完",
      "notes": ""
    },
    {
      "hookId": "伏笔-铁匣刻字\"别走\"",
      "startChapter": 0,
      "type": "open",
      "status": "open",
      "lastAdvancedChapter": 0,
      "expectedPayoff": "\"别走\"含义仍待解读/阿纱询问\"有没有收东西\"暗示了解铁匣",
      "notes": ""
    },
    {
      "hookId": "伏笔-它们怕光",
      "startChapter": 0,
      "type": "悬置",
      "status": "open",
      "lastAdvancedChapter": 0,
      "expectedPayoff": "",
      "notes": ""
    },
    {
      "hookId": "伏笔-两年前的女人",
      "startChapter": 26,
      "type": "伏笔",
      "status": "open",
      "lastAdvancedChapter": 40,
      "expectedPayoff": "待展开",
      "notes": "女人收到灰白草茎后失踪/\"走了就没再回来\"/钱进两年前见过"
    },
    {
      "hookId": "伏笔-别看它们的眼睛",
      "startChapter": 65,
      "type": "悬念",
      "status": "open",
      "lastAdvancedChapter": 0,
      "expectedPayoff": "待展开",
      "notes": ""
    },
    {
      "hookId": "伏笔-灰白草茎规则",
      "startChapter": 0,
      "type": "open",
      "status": "progressing",
      "lastAdvancedChapter": 0,
      "expectedPayoff": "-",
      "notes": ""
    },
    {
      "hookId": "伏笔-钱进的遗言\"巢\"",
      "startChapter": 64,
      "type": "伏笔",
      "status": "open",
      "lastAdvancedChapter": 0,
      "expectedPayoff": "待展开",
      "notes": "巢是什么？在哪里？与\"它们\"的关系？"
    },
    {
      "hookId": "伏笔-洞穴外逼近威胁",
      "startChapter": 0,
      "type": "待展开",
      "status": "open",
      "lastAdvancedChapter": 36,
      "expectedPayoff": "**待展开**",
      "notes": "\"它们\"已出现在破庙附近"
    },
    {
      "hookId": "伏笔-阿纱的眼圈红",
      "startChapter": 64,
      "type": "伏笔",
      "status": "open",
      "lastAdvancedChapter": 0,
      "expectedPayoff": "待展开",
      "notes": "她与铁匣/活物有什么关系？"
    },
    {
      "hookId": "伏笔-钱进\"不能不要\"",
      "startChapter": 0,
      "type": "open",
      "status": "open",
      "lastAdvancedChapter": 0,
      "expectedPayoff": "铁匣/草茎/或其他→待65章明确",
      "notes": ""
    },
    {
      "hookId": "伏笔-SU40\"它们\"的身份",
      "startChapter": 0,
      "type": "伏笔",
      "status": "open",
      "lastAdvancedChapter": 29,
      "expectedPayoff": "待展开",
      "notes": "钱进临死透露/\"巢\"/与洞穴深处阴影/灰白草茎/尸体薄膜"
    },
    {
      "hookId": "伏笔-断手活物下落",
      "startChapter": 0,
      "type": "伏笔",
      "status": "open",
      "lastAdvancedChapter": 0,
      "expectedPayoff": "活物×4已死/下落待查",
      "notes": ""
    },
    {
      "hookId": "伏笔-SU006苏青禾",
      "startChapter": 4,
      "type": "支线",
      "status": "open",
      "lastAdvancedChapter": 53,
      "expectedPayoff": "**连续11章未提及**",
      "notes": "**必须下一章（65章）处理/已超临界点**"
    },
    {
      "hookId": "伏笔-活物怕光",
      "startChapter": 0,
      "type": "悬置",
      "status": "open",
      "lastAdvancedChapter": 0,
      "expectedPayoff": "",
      "notes": ""
    },
    {
      "hookId": "伏笔-铁匣刻字",
      "startChapter": 0,
      "type": "open",
      "status": "open",
      "lastAdvancedChapter": 0,
      "expectedPayoff": "\"别走\"→\"别打开/别看/别碰/别留在手里\"→多义待解",
      "notes": ""
    },
    {
      "hookId": "伏笔-灰白絮状物",
      "startChapter": 0,
      "type": "open",
      "status": "open",
      "lastAdvancedChapter": 0,
      "expectedPayoff": "64章确认",
      "notes": ""
    },
    {
      "hookId": "伏笔-断手活物（SP039）",
      "startChapter": 0,
      "type": "**已回收**",
      "status": "open",
      "lastAdvancedChapter": 0,
      "expectedPayoff": "60章切断→64章确认匣内仅三只，断手已分离→伏笔完结",
      "notes": ""
    },
    {
      "hookId": "伏笔-SP006苏青禾安全",
      "startChapter": 53,
      "type": "**主线支线**",
      "status": "open",
      "lastAdvancedChapter": 53,
      "expectedPayoff": "**64章仍只有\"想起\"→极度警告→65章必须处理**",
      "notes": "**53章安置灌木丛→64章仅想起（十天）→连续11章未实际推进→读者期待积压超临界点→65章必须：确认安全/出现危险/明确线索→不能以\"想起\"一笔带过**"
    },
    {
      "hookId": "伏笔-它们是谁",
      "startChapter": 0,
      "type": "open",
      "status": "open",
      "lastAdvancedChapter": 0,
      "expectedPayoff": "穴居人变成的灰败人？→与阿纱不同→给铁匣/给东西的存在",
      "notes": ""
    },
    {
      "hookId": "伏笔-山中异常安静",
      "startChapter": 0,
      "type": "open",
      "status": "open",
      "lastAdvancedChapter": 0,
      "expectedPayoff": "鸟虫声消失→\"它们\"的存在压住声响",
      "notes": ""
    },
    {
      "hookId": "伏笔-铁匣刻字\"别——\"",
      "startChapter": 0,
      "type": "open",
      "status": "open",
      "lastAdvancedChapter": 0,
      "expectedPayoff": "新解读：别留在手里/别送回去？→与草茎规则矛盾",
      "notes": ""
    },
    {
      "hookId": "伏笔-两年前女人",
      "startChapter": 0,
      "type": "open",
      "status": "open",
      "lastAdvancedChapter": 0,
      "expectedPayoff": "收到灰白草茎/\"走了没再回来\"→非苏青禾（时间线矛盾）",
      "notes": ""
    },
    {
      "hookId": "H002",
      "startChapter": 25,
      "type": "支线",
      "status": "open",
      "lastAdvancedChapter": 27,
      "expectedPayoff": "待定",
      "notes": "苏青禾身世（赵破天女儿）；**本章确认被捕关押中/令牌被夺**"
    },
    {
      "hookId": "H006",
      "startChapter": 11,
      "type": "伏笔",
      "status": "open",
      "lastAdvancedChapter": 0,
      "expectedPayoff": "待回收",
      "notes": "五年前苏父为治眼去黑松林"
    },
    {
      "hookId": "H012",
      "startChapter": 0,
      "type": "progressing",
      "status": "open",
      "lastAdvancedChapter": 0,
      "expectedPayoff": "黑松林地图交换",
      "notes": ""
    },
    {
      "hookId": "H016",
      "startChapter": 0,
      "type": "待展开",
      "status": "open",
      "lastAdvancedChapter": 6,
      "expectedPayoff": "待推进",
      "notes": ""
    },
    {
      "hookId": "H018",
      "startChapter": 0,
      "type": "open",
      "status": "open",
      "lastAdvancedChapter": 0,
      "expectedPayoff": "",
      "notes": ""
    },
    {
      "hookId": "H021",
      "startChapter": 0,
      "type": "progressing",
      "status": "open",
      "lastAdvancedChapter": 0,
      "expectedPayoff": "前两天刚从林子出来/伤了元气",
      "notes": ""
    },
    {
      "hookId": "H024",
      "startChapter": 0,
      "type": "progressing",
      "status": "open",
      "lastAdvancedChapter": 0,
      "expectedPayoff": "-",
      "notes": ""
    },
    {
      "hookId": "H025",
      "startChapter": 0,
      "type": "open",
      "status": "open",
      "lastAdvancedChapter": 0,
      "expectedPayoff": "",
      "notes": ""
    },
    {
      "hookId": "H026",
      "startChapter": 0,
      "type": "open",
      "status": "open",
      "lastAdvancedChapter": 0,
      "expectedPayoff": "",
      "notes": ""
    },
    {
      "hookId": "H027",
      "startChapter": 0,
      "type": "progressing",
      "status": "open",
      "lastAdvancedChapter": 0,
      "expectedPayoff": "-",
      "notes": "待展开"
    },
    {
      "hookId": "H011",
      "startChapter": 0,
      "type": "open",
      "status": "open",
      "lastAdvancedChapter": 0,
      "expectedPayoff": "待后续章节确认状态",
      "notes": "需后续章节确认状态"
    },
    {
      "hookId": "H013",
      "startChapter": 0,
      "type": "progressing",
      "status": "open",
      "lastAdvancedChapter": 0,
      "expectedPayoff": "需进入黑松林",
      "notes": ""
    },
    {
      "hookId": "H029",
      "startChapter": 0,
      "type": "open",
      "status": "open",
      "lastAdvancedChapter": 12,
      "expectedPayoff": "后续章节",
      "notes": "三叔透露父亲死因被拦截"
    },
    {
      "hookId": "H030",
      "startChapter": 0,
      "type": "open",
      "status": "open",
      "lastAdvancedChapter": 12,
      "expectedPayoff": "后续章节",
      "notes": "陆鸢对陆沉的怨恨"
    },
    {
      "hookId": "H031",
      "startChapter": 0,
      "type": "progressing",
      "status": "open",
      "lastAdvancedChapter": 0,
      "expectedPayoff": "-",
      "notes": ""
    },
    {
      "hookId": "H032",
      "startChapter": 0,
      "type": "progressing",
      "status": "open",
      "lastAdvancedChapter": 45,
      "expectedPayoff": "待定",
      "notes": "陆沉与叔父遗言/\"不干净\"的东西/铁匣来历"
    },
    {
      "hookId": "H033",
      "startChapter": 0,
      "type": "open",
      "status": "open",
      "lastAdvancedChapter": 12,
      "expectedPayoff": "13章",
      "notes": "黑松林任务"
    },
    {
      "hookId": "H003",
      "startChapter": 3,
      "type": "剧情",
      "status": "open",
      "lastAdvancedChapter": 0,
      "expectedPayoff": "待回收",
      "notes": "暗室玉佩被取走"
    },
    {
      "hookId": "H008",
      "startChapter": 0,
      "type": "13",
      "status": "open",
      "lastAdvancedChapter": 0,
      "expectedPayoff": "",
      "notes": ""
    },
    {
      "hookId": "H014",
      "startChapter": 0,
      "type": "progressing",
      "status": "open",
      "lastAdvancedChapter": 0,
      "expectedPayoff": "与断脊刀持有者身份关联",
      "notes": ""
    },
    {
      "hookId": "H015",
      "startChapter": 0,
      "type": "progressing",
      "status": "open",
      "lastAdvancedChapter": 33,
      "expectedPayoff": "待展开",
      "notes": "苏青禾透露：苏婉/\"那块牌子害死了她\"/有人反复问苏青禾她娘的名字"
    },
    {
      "hookId": "H020",
      "startChapter": 0,
      "type": "13",
      "status": "open",
      "lastAdvancedChapter": 0,
      "expectedPayoff": "",
      "notes": ""
    },
    {
      "hookId": "H034",
      "startChapter": 0,
      "type": "待展开",
      "status": "open",
      "lastAdvancedChapter": 0,
      "expectedPayoff": "待展开",
      "notes": "待展开"
    },
    {
      "hookId": "H035",
      "startChapter": 0,
      "type": "open",
      "status": "open",
      "lastAdvancedChapter": 0,
      "expectedPayoff": "-",
      "notes": ""
    },
    {
      "hookId": "H036",
      "startChapter": 0,
      "type": "悬念",
      "status": "open",
      "lastAdvancedChapter": 0,
      "expectedPayoff": "",
      "notes": ""
    },
    {
      "hookId": "H037",
      "startChapter": 0,
      "type": "悬念",
      "status": "open",
      "lastAdvancedChapter": 0,
      "expectedPayoff": "",
      "notes": ""
    },
    {
      "hookId": "H001",
      "startChapter": 0,
      "type": "open",
      "status": "open",
      "lastAdvancedChapter": 0,
      "expectedPayoff": "陆家恩怨相关——SP001老头已透露父亲旧人网络",
      "notes": ""
    },
    {
      "hookId": "H038",
      "startChapter": 0,
      "type": "悬念",
      "status": "open",
      "lastAdvancedChapter": 0,
      "expectedPayoff": "",
      "notes": ""
    },
    {
      "hookId": "H039",
      "startChapter": 0,
      "type": "progressing",
      "status": "open",
      "lastAdvancedChapter": 0,
      "expectedPayoff": "钱进遗言整理（\"它们\"/\"巢\"/\"别看眼睛\"/\"不能不要\"）",
      "notes": ""
    },
    {
      "hookId": "H040",
      "startChapter": 0,
      "type": "progressing",
      "status": "open",
      "lastAdvancedChapter": 0,
      "expectedPayoff": "黑虎帮觊觎/孟三往北/乱葬岗方向",
      "notes": ""
    },
    {
      "hookId": "H009",
      "startChapter": 0,
      "type": "待展开",
      "status": "open",
      "lastAdvancedChapter": 14,
      "expectedPayoff": "待推进",
      "notes": ""
    },
    {
      "hookId": "H010",
      "startChapter": 13,
      "type": "剧情",
      "status": "resolved",
      "lastAdvancedChapter": 0,
      "expectedPayoff": "待展开",
      "notes": "钱通欲换取断脊刀"
    },
    {
      "hookId": "H041",
      "startChapter": 0,
      "type": "open",
      "status": "open",
      "lastAdvancedChapter": 0,
      "expectedPayoff": "待定",
      "notes": "待展开"
    },
    {
      "hookId": "H042",
      "startChapter": 0,
      "type": "open",
      "status": "open",
      "lastAdvancedChapter": 0,
      "expectedPayoff": "待展开",
      "notes": ""
    },
    {
      "hookId": "H043",
      "startChapter": 0,
      "type": "open",
      "status": "open",
      "lastAdvancedChapter": 0,
      "expectedPayoff": "本章提及需跟进",
      "notes": ""
    },
    {
      "hookId": "H044",
      "startChapter": 0,
      "type": "open",
      "status": "open",
      "lastAdvancedChapter": 0,
      "expectedPayoff": "待展开",
      "notes": "断手活物/第四只手状态"
    },
    {
      "hookId": "H045",
      "startChapter": 0,
      "type": "**伏笔**",
      "status": "open",
      "lastAdvancedChapter": 0,
      "expectedPayoff": "待展开",
      "notes": "状态卡中标注，待查原始文档"
    },
    {
      "hookId": "H061",
      "startChapter": 16,
      "type": "剧情",
      "status": "progressing",
      "lastAdvancedChapter": 16,
      "expectedPayoff": "待回收",
      "notes": "铁牌来历不明。→ 本章确认：苏父从黑松林带回/与老郎中有关联"
    },
    {
      "hookId": "H062",
      "startChapter": 16,
      "type": "剧情",
      "status": "resolved",
      "lastAdvancedChapter": 16,
      "expectedPayoff": "-",
      "notes": "入城成功。→ 延续到本章"
    },
    {
      "hookId": "H056",
      "startChapter": 16,
      "type": "剧情",
      "status": "progressing",
      "lastAdvancedChapter": 17,
      "expectedPayoff": "待回收",
      "notes": "钱通掌权。→ 本章确认：周铁山已死/钱通今晚柳巷东清场"
    },
    {
      "hookId": "阶段",
      "startChapter": 0,
      "type": "章节",
      "status": "open",
      "lastAdvancedChapter": 0,
      "expectedPayoff": "",
      "notes": ""
    },
    {
      "hookId": "苏青禾被救出",
      "startChapter": 0,
      "type": "11",
      "status": "open",
      "lastAdvancedChapter": 0,
      "expectedPayoff": "",
      "notes": ""
    },
    {
      "hookId": "同行前往陆家村",
      "startChapter": 0,
      "type": "12",
      "status": "open",
      "lastAdvancedChapter": 0,
      "expectedPayoff": "",
      "notes": ""
    },
    {
      "hookId": "被留在山脊躲避",
      "startChapter": 0,
      "type": "12",
      "status": "open",
      "lastAdvancedChapter": 0,
      "expectedPayoff": "",
      "notes": ""
    },
    {
      "hookId": "山道等待",
      "startChapter": 0,
      "type": "12",
      "status": "open",
      "lastAdvancedChapter": 0,
      "expectedPayoff": "",
      "notes": ""
    },
    {
      "hookId": "被安置灌木丛躲避",
      "startChapter": 0,
      "type": "12",
      "status": "open",
      "lastAdvancedChapter": 0,
      "expectedPayoff": "",
      "notes": ""
    },
    {
      "hookId": "被黑虎帮找到并关押",
      "startChapter": 0,
      "type": "**16**",
      "status": "open",
      "lastAdvancedChapter": 0,
      "expectedPayoff": "",
      "notes": ""
    },
    {
      "hookId": "营救苏青禾",
      "startChapter": 0,
      "type": "-",
      "status": "open",
      "lastAdvancedChapter": 0,
      "expectedPayoff": "",
      "notes": ""
    },
    {
      "hookId": "H055",
      "startChapter": 16,
      "type": "剧情",
      "status": "progressing",
      "lastAdvancedChapter": 17,
      "expectedPayoff": "待回收",
      "notes": "苏父重伤归来，从黑松林带回东西。→ 本章皮货老头补充：半死不活躺三天"
    },
    {
      "hookId": "H057",
      "startChapter": 16,
      "type": "剧情",
      "status": "progressing",
      "lastAdvancedChapter": 17,
      "expectedPayoff": "待回收",
      "notes": "钱通找\"使刀的皮肉境小子\"。→ 本章：陆沉身份暴露被盯梢"
    },
    {
      "hookId": "H068",
      "startChapter": 17,
      "type": "剧情",
      "status": "open",
      "lastAdvancedChapter": 17,
      "expectedPayoff": "待回收",
      "notes": "主角身份已暴露/被确认还活着/黑虎帮正在穷人区搜索"
    },
    {
      "hookId": "H069",
      "startChapter": 17,
      "type": "剧情",
      "status": "open",
      "lastAdvancedChapter": 17,
      "expectedPayoff": "待回收",
      "notes": "皮货老头身份存疑（可能是黑虎帮线人或内部人）"
    },
    {
      "hookId": "H070",
      "startChapter": 17,
      "type": "剧情",
      "status": "open",
      "lastAdvancedChapter": 17,
      "expectedPayoff": "待回收",
      "notes": "苏父带回的\"贵重东西\"——价值极高，比苏青禾重要得多"
    },
    {
      "hookId": "H071",
      "startChapter": 17,
      "type": "剧情",
      "status": "open",
      "lastAdvancedChapter": 17,
      "expectedPayoff": "待回收",
      "notes": "钱通意图分析——不是交易，是吞掉"
    },
    {
      "hookId": "H072",
      "startChapter": 17,
      "type": "剧情",
      "status": "open",
      "lastAdvancedChapter": 17,
      "expectedPayoff": "待回收",
      "notes": "老郎中遗言纸条（\"林中有巢/入者无归/别走\"）与骨庙刻字一致"
    },
    {
      "hookId": "H073",
      "startChapter": 0,
      "type": "resolved",
      "status": "open",
      "lastAdvancedChapter": 0,
      "expectedPayoff": "老郎中动机（苏老实救命恩）→**第21章回收**",
      "notes": ""
    },
    {
      "hookId": "H052",
      "startChapter": 16,
      "type": "伏笔",
      "status": "open",
      "lastAdvancedChapter": 19,
      "expectedPayoff": "-",
      "notes": "铁骨狼群。延续"
    },
    {
      "hookId": "H074",
      "startChapter": 0,
      "type": "resolved",
      "status": "open",
      "lastAdvancedChapter": 0,
      "expectedPayoff": "柳巷东时间（今晚/死局）→**第21章回收**",
      "notes": ""
    },
    {
      "hookId": "H075",
      "startChapter": 0,
      "type": "resolved",
      "status": "open",
      "lastAdvancedChapter": 0,
      "expectedPayoff": "苏父东西来源（抵账品/不干净）→**第21章回收**",
      "notes": ""
    },
    {
      "hookId": "H073续",
      "startChapter": 19,
      "type": "剧情",
      "status": "open",
      "lastAdvancedChapter": 19,
      "expectedPayoff": "待回收",
      "notes": "**新增推理：老郎中可能是在挑人——观察陆沉是否值得帮/可能是第三方势力需要的人/三天后柳巷东可能有三方博弈**"
    },
    {
      "hookId": "H076",
      "startChapter": 19,
      "type": "**剧情**",
      "status": "open",
      "lastAdvancedChapter": 19,
      "expectedPayoff": "**待回收**",
      "notes": "**黑虎帮包围圈收缩——\"那小子伤了，跑不远，就在附近\"/时间比三天更紧迫**"
    },
    {
      "hookId": "H077",
      "startChapter": 0,
      "type": "open",
      "status": "open",
      "lastAdvancedChapter": 20,
      "expectedPayoff": "已回收",
      "notes": "舵把子称呼已确认"
    },
    {
      "hookId": "SU40\"它们\"的身份",
      "startChapter": 0,
      "type": "悬念",
      "status": "open",
      "lastAdvancedChapter": 36,
      "expectedPayoff": "**待展开**",
      "notes": "老人提及/正在逼近/与灵脉相关"
    },
    {
      "hookId": "H078",
      "startChapter": 0,
      "type": "open",
      "status": "open",
      "lastAdvancedChapter": 0,
      "expectedPayoff": "**孙麻子身份明确：城中蛇头/二十年城门经验/老苏救命恩人**",
      "notes": ""
    },
    {
      "hookId": "H079",
      "startChapter": 0,
      "type": "open",
      "status": "open",
      "lastAdvancedChapter": 0,
      "expectedPayoff": "**老郎中命运确认：下午被黑虎帮带走/生死不明/在柳巷东撑时间**",
      "notes": ""
    },
    {
      "hookId": "H080",
      "startChapter": 0,
      "type": "open",
      "status": "open",
      "lastAdvancedChapter": 0,
      "expectedPayoff": "**老郎中与黑虎帮恩怨确认：派苏老实去黑松林收账/苏老实带回不干净的东西**",
      "notes": ""
    },
    {
      "hookId": "H081",
      "startChapter": 0,
      "type": "open",
      "status": "open",
      "lastAdvancedChapter": 0,
      "expectedPayoff": "**苏青禾位置确认：柳巷东第三条巷子尽头/枯井边/脚踝断/被当饵**",
      "notes": ""
    },
    {
      "hookId": "H082",
      "startChapter": 0,
      "type": "open",
      "status": "open",
      "lastAdvancedChapter": 21,
      "expectedPayoff": "待回收",
      "notes": "柳巷东巡逻规律发现（约一刻钟间隔）"
    },
    {
      "hookId": "H083",
      "startChapter": 0,
      "type": "resolved",
      "status": "open",
      "lastAdvancedChapter": 0,
      "expectedPayoff": "22",
      "notes": "已解决"
    },
    {
      "hookId": "H084",
      "startChapter": 0,
      "type": "resolved",
      "status": "open",
      "lastAdvancedChapter": 0,
      "expectedPayoff": "22",
      "notes": "已解决"
    },
    {
      "hookId": "H085",
      "startChapter": 0,
      "type": "open",
      "status": "open",
      "lastAdvancedChapter": 0,
      "expectedPayoff": "22-23",
      "notes": "**新增钩子：铁牌正面闭眼图案/背面\"别走\"/土腥味+腐甜味/与黑松林/穴居人/青云宗可能相关**"
    },
    {
      "hookId": "H086",
      "startChapter": 0,
      "type": "progressing",
      "status": "open",
      "lastAdvancedChapter": 0,
      "expectedPayoff": "23",
      "notes": "23-24"
    },
    {
      "hookId": "H087",
      "startChapter": 0,
      "type": "progressing",
      "status": "open",
      "lastAdvancedChapter": 0,
      "expectedPayoff": "23",
      "notes": "23-24"
    },
    {
      "hookId": "H088",
      "startChapter": 0,
      "type": "open",
      "status": "open",
      "lastAdvancedChapter": 0,
      "expectedPayoff": "23",
      "notes": "23"
    },
    {
      "hookId": "H054",
      "startChapter": 17,
      "type": "剧情",
      "status": "progressing",
      "lastAdvancedChapter": 17,
      "expectedPayoff": "待回收",
      "notes": "苏父重伤归来。"
    },
    {
      "hookId": "H059",
      "startChapter": 16,
      "type": "剧情",
      "status": "open",
      "lastAdvancedChapter": 17,
      "expectedPayoff": "待回收",
      "notes": "苏青禾被扣。→ 本章确认：今晚柳巷东当筹码"
    },
    {
      "hookId": "SU40",
      "startChapter": 0,
      "type": "open",
      "status": "open",
      "lastAdvancedChapter": 0,
      "expectedPayoff": "\"它们\"的身份：钱进临死透露/穴居人/灰白皮肤/尸体薄膜/巢",
      "notes": ""
    },
    {
      "hookId": "两年前女人",
      "startChapter": 0,
      "type": "open",
      "status": "open",
      "lastAdvancedChapter": 0,
      "expectedPayoff": "两年前女人/灰白草茎/\"走了没再回来\"→时间线矛盾待解",
      "notes": ""
    },
    {
      "hookId": "它们怕光",
      "startChapter": 0,
      "type": "伏笔",
      "status": "open",
      "lastAdvancedChapter": 29,
      "expectedPayoff": "待定",
      "notes": "活物怕光但不完全怕/可利用阴影控制"
    },
    {
      "hookId": "H058",
      "startChapter": 17,
      "type": "剧情",
      "status": "progressing",
      "lastAdvancedChapter": 17,
      "expectedPayoff": "待回收",
      "notes": "老郎中失踪。→ 本章皮货老头透露：老郎中看完苏父后当晚就跑"
    },
    {
      "hookId": "H060",
      "startChapter": 17,
      "type": "剧情",
      "status": "open",
      "lastAdvancedChapter": 17,
      "expectedPayoff": "待回收",
      "notes": "柳巷东只有一个出口。→ 本章皮货老头警告"
    },
    {
      "hookId": "H089",
      "startChapter": 0,
      "type": "progressing",
      "status": "open",
      "lastAdvancedChapter": 0,
      "expectedPayoff": "钱进的完整计划——为何要灭苏老实/老郎中/陆沉？",
      "notes": ""
    },
    {
      "hookId": "SP039",
      "startChapter": 0,
      "type": "**推进**",
      "status": "open",
      "lastAdvancedChapter": 44,
      "expectedPayoff": "待展开",
      "notes": "断手持续在匣壁上爬动→活物曾试图爬向苏青禾→被阻止"
    },
    {
      "hookId": "活物怕光",
      "startChapter": 0,
      "type": "open",
      "status": "open",
      "lastAdvancedChapter": 0,
      "expectedPayoff": "三只活物怕光特性/可利用阴影控制",
      "notes": ""
    },
    {
      "hookId": "灰白絮状物",
      "startChapter": 0,
      "type": "open",
      "status": "open",
      "lastAdvancedChapter": 0,
      "expectedPayoff": "絮状物被从内拱开/是巢穴或保护层",
      "notes": ""
    },
    {
      "hookId": "H090",
      "startChapter": 0,
      "type": "open",
      "status": "open",
      "lastAdvancedChapter": 0,
      "expectedPayoff": "钱进的完整计划——为何要灭苏老实/老郎中/陆沉？荒卫令牌对他有何价值？→钱进重兵守城南门，但未派人主力搜查枯井，动机不明",
      "notes": ""
    },
    {
      "hookId": "H091",
      "startChapter": 0,
      "type": "resolved",
      "status": "open",
      "lastAdvancedChapter": 0,
      "expectedPayoff": "陆沉枯井困局——如何脱身？**→已脱困，威胁仍在井底深处未追出**",
      "notes": ""
    },
    {
      "hookId": "H092",
      "startChapter": 0,
      "type": "open",
      "status": "open",
      "lastAdvancedChapter": 0,
      "expectedPayoff": "荒卫令牌来历——37号编号/荒卫司含义待解读",
      "notes": ""
    },
    {
      "hookId": "SP006（苏青禾线）",
      "startChapter": 0,
      "type": "**open→关键推进**",
      "status": "open",
      "lastAdvancedChapter": 21,
      "expectedPayoff": "**待回收**",
      "notes": "**孙麻子确认苏青禾位置：柳巷东第三条巷子尽头枯井旁/脚踝断/今晚用于钓鱼→下一章需推进营救**"
    },
    {
      "hookId": "SP006",
      "startChapter": 0,
      "type": "支线",
      "status": "open",
      "lastAdvancedChapter": 27,
      "expectedPayoff": "待定",
      "notes": "苏青禾营救——**位置确认：城中/钱进手上**"
    },
    {
      "hookId": "H095",
      "startChapter": 25,
      "type": "剧情",
      "status": "open",
      "lastAdvancedChapter": 27,
      "expectedPayoff": "待定",
      "notes": "孟三与火场有关/知道三十七号令牌含义/\"老东家\"出现"
    },
    {
      "hookId": "H096",
      "startChapter": 0,
      "type": "open",
      "status": "open",
      "lastAdvancedChapter": 0,
      "expectedPayoff": "老头认识陆沉——已解释为欠父亲恩情",
      "notes": ""
    },
    {
      "hookId": "H097",
      "startChapter": 25,
      "type": "剧情",
      "status": "open",
      "lastAdvancedChapter": 26,
      "expectedPayoff": "待定",
      "notes": "\"另一个声音\"是陆沉父亲的旧人；此人帮陆沉挡了追兵；**拒绝透露姓名**"
    },
    {
      "hookId": "H098",
      "startChapter": 0,
      "type": "open",
      "status": "open",
      "lastAdvancedChapter": 0,
      "expectedPayoff": "孟三认令牌：手摸刀柄/汗从鬓角冒出/周执事当年调他出校场→背后动机待查",
      "notes": ""
    },
    {
      "hookId": "H099",
      "startChapter": 0,
      "type": "open",
      "status": "open",
      "lastAdvancedChapter": 0,
      "expectedPayoff": "孟三背后的人：周执事/青云宗外门执事/府城势力/下令清剿荒卫司",
      "notes": ""
    },
    {
      "hookId": "H093",
      "startChapter": 0,
      "type": "open",
      "status": "open",
      "lastAdvancedChapter": 0,
      "expectedPayoff": "钱进为何不派主力搜查枯井？是真不知道陆沉在里面，还是故意放过？→推断：钱进认定陆沉会从城南门出城，所以枯井不值得浪费人手",
      "notes": ""
    },
    {
      "hookId": "H094",
      "startChapter": 0,
      "type": "open",
      "status": "open",
      "lastAdvancedChapter": 0,
      "expectedPayoff": "孙麻子带苏青禾走的是城南门乱葬岗方向（钱进透露的假消息），但搜完没人——他们成功逃脱了吗？还是被抓了？→第25章确认：孙麻子改走城西，已留锅灰暗号",
      "notes": ""
    },
    {
      "hookId": "H100",
      "startChapter": 0,
      "type": "open",
      "status": "open",
      "lastAdvancedChapter": 0,
      "expectedPayoff": "令牌来源疑问：陆沉父亲的令牌？马七师兄的令牌？十三年前遗物",
      "notes": ""
    },
    {
      "hookId": "H103（监视者身份）",
      "startChapter": 29,
      "type": "悬念",
      "status": "open",
      "lastAdvancedChapter": 32,
      "expectedPayoff": "待展开",
      "notes": "城里布鞋/例行巡逻/老东家关联"
    },
    {
      "hookId": "H106（神秘老人身份）",
      "startChapter": 29,
      "type": "剧情",
      "status": "open",
      "lastAdvancedChapter": 31,
      "expectedPayoff": "**待展开**",
      "notes": "神秘老人登场：佝偻、老农面孔、动作极快，与十三年前救人者特征（'那双手很大很有力'）产生关联；救人方式奇怪（不图钱不图名）；是否为同一人待查"
    },
    {
      "hookId": "mystery-陆沉与神秘老人是否再相遇",
      "startChapter": 30,
      "type": "mystery",
      "status": "open",
      "lastAdvancedChapter": 31,
      "expectedPayoff": "陆沉与神秘老人是否再相遇；老人目的",
      "notes": "神秘老人救陆沉后不答身份消失，为何出手相救？是否与十三年前有关？是否监视者之一？"
    },
    {
      "hookId": "H001（令牌刀痕）",
      "startChapter": 29,
      "type": "剧情",
      "status": "open",
      "lastAdvancedChapter": 30,
      "expectedPayoff": "待展开",
      "notes": "令牌背面刀痕：系带断口角度有些歪，腕力不稳但角度准，一刀切断系带，有人曾将此令牌从某人身上取下"
    },
    {
      "hookId": "SP039（断手活物）",
      "startChapter": 39,
      "type": "悬念",
      "status": "open",
      "lastAdvancedChapter": 40,
      "expectedPayoff": "65章明确交代",
      "notes": "匣内活物/第四只（断手）状态未交代"
    },
    {
      "hookId": "章节",
      "startChapter": 0,
      "type": "出场人物",
      "status": "open",
      "lastAdvancedChapter": 0,
      "expectedPayoff": "伏笔动态",
      "notes": "情绪基调"
    },
    {
      "hookId": "29",
      "startChapter": 0,
      "type": "陆沉（独角戏）",
      "status": "open",
      "lastAdvancedChapter": 0,
      "expectedPayoff": "H001推进（令牌刀痕、十三年前救人者）；H103推进（监视者持续出现）；H104/H105/H106新增（刀痕、空车、救人者）",
      "notes": "警觉→压抑→疑虑→回忆→坚定→警觉"
    },
    {
      "hookId": "30",
      "startChapter": 0,
      "type": "陆沉、赵三爷（死）、神秘老人、跪地打手（死）",
      "status": "open",
      "lastAdvancedChapter": 8,
      "expectedPayoff": "H106推进（神秘老人与十三年前救人者关联）；H103持续（监视者身份未揭示）",
      "notes": "紧绷→血腥→冷峻"
    },
    {
      "hookId": "31",
      "startChapter": 0,
      "type": "**陆沉**",
      "status": "open",
      "lastAdvancedChapter": 0,
      "expectedPayoff": "**H103推进（监视者身份缩小到老东家）；H106持续（神秘老人悬念保持）；新增：柳巷东侦察信息（两拨人/灯光位置/干活人脚印）**",
      "notes": "**警觉→压抑→疑虑→坚定→警觉→冷峻**"
    },
    {
      "hookId": "H001-mystery-陆沉与令牌",
      "startChapter": 0,
      "type": "progressing",
      "status": "open",
      "lastAdvancedChapter": 0,
      "expectedPayoff": "老人身份/杀人取牌动机",
      "notes": ""
    },
    {
      "hookId": "H103-监视者身份",
      "startChapter": 0,
      "type": "progressing",
      "status": "open",
      "lastAdvancedChapter": 0,
      "expectedPayoff": "监视者身份/老东家目的",
      "notes": ""
    },
    {
      "hookId": "H106-神秘老人",
      "startChapter": 0,
      "type": "progressing",
      "status": "open",
      "lastAdvancedChapter": 0,
      "expectedPayoff": "老人与十三年前救人者关系",
      "notes": ""
    },
    {
      "hookId": "SP006-苏青禾营救窗口",
      "startChapter": 0,
      "type": "progressing",
      "status": "open",
      "lastAdvancedChapter": 0,
      "expectedPayoff": "明晚行动",
      "notes": ""
    },
    {
      "hookId": "SP025-孟三未归",
      "startChapter": 0,
      "type": "closed",
      "status": "open",
      "lastAdvancedChapter": 0,
      "expectedPayoff": "已删除",
      "notes": ""
    },
    {
      "hookId": "SP039-断手活物去向",
      "startChapter": 0,
      "type": "open",
      "status": "open",
      "lastAdvancedChapter": 0,
      "expectedPayoff": "需进入黑松林",
      "notes": ""
    },
    {
      "hookId": "H013-黑松林",
      "startChapter": 0,
      "type": "progressing",
      "status": "open",
      "lastAdvancedChapter": 0,
      "expectedPayoff": "需进入黑松林",
      "notes": ""
    },
    {
      "hookId": "H014-断脊刀持有者",
      "startChapter": 0,
      "type": "progressing",
      "status": "open",
      "lastAdvancedChapter": 0,
      "expectedPayoff": "待展开",
      "notes": ""
    },
    {
      "hookId": "mystery-陆沉与神秘老-人是否再相遇-老人目的",
      "startChapter": 0,
      "type": "open",
      "status": "open",
      "lastAdvancedChapter": 0,
      "expectedPayoff": "老人再次出手相救；杀人翻东西赶时间；取令牌不取人（赶时间）；老人救人的手（大/有力）与老人杀人的手（骨节粗/指甲黑泥）不是同一双手",
      "notes": ""
    },
    {
      "hookId": "H106",
      "startChapter": 0,
      "type": "open",
      "status": "open",
      "lastAdvancedChapter": 33,
      "expectedPayoff": "待展开",
      "notes": "老人第三次出现并主动接触（指路+警告）；陆沉接受了帮助但未追问；\"令牌的事别查了\"新增悬念"
    },
    {
      "hookId": "SP021",
      "startChapter": 0,
      "type": "open",
      "status": "open",
      "lastAdvancedChapter": 33,
      "expectedPayoff": "待展开",
      "notes": "老东家的人被钱进抓关押；令牌可能是钱进抓人的动机之一"
    },
    {
      "hookId": "SP027",
      "startChapter": 0,
      "type": "open",
      "status": "open",
      "lastAdvancedChapter": 33,
      "expectedPayoff": "待展开",
      "notes": "令牌成对之谜；老东家追令牌；老人警告\"令牌别查\""
    },
    {
      "hookId": "H103",
      "startChapter": 0,
      "type": "**新增**",
      "status": "open",
      "lastAdvancedChapter": 0,
      "expectedPayoff": "**周执事身份：下令清剿荒卫司/马七与其有旧账/府城势力/孟三保护伞**",
      "notes": ""
    },
    {
      "hookId": "mystery-陆沉与神秘老人是否再相遇-老人目的",
      "startChapter": 0,
      "type": "open",
      "status": "open",
      "lastAdvancedChapter": 33,
      "expectedPayoff": "待展开",
      "notes": "老人第三次出现（沟渠跟踪/指路/\"令牌的事别查了，查下去要死人的\"）；老人仍在暗中跟随陆沉，目的仍不明"
    },
    {
      "hookId": "SP001",
      "startChapter": 0,
      "type": "支线",
      "status": "open",
      "lastAdvancedChapter": 27,
      "expectedPayoff": "待定",
      "notes": "陆家恩怨——**推进：孟三、火场、老东家、三十七号含义**"
    },
    {
      "hookId": "伏笔-苏婉身份",
      "startChapter": 0,
      "type": "**open**",
      "status": "open",
      "lastAdvancedChapter": 34,
      "expectedPayoff": "待展开",
      "notes": "**苏青禾之母/死于十三年前山火/苏老实说\"那块牌子害死了她\"/有人反复问苏青禾她娘的名字/与令牌关联待查**"
    },
    {
      "hookId": "伏笔-老东家人被抓原因",
      "startChapter": 0,
      "type": "**open**",
      "status": "open",
      "lastAdvancedChapter": 34,
      "expectedPayoff": "待展开",
      "notes": "**老东家的人被抓/\"令牌是我给老东家的\"/\"真正令牌在——\"未说完/宁死不说老东家名字/老东家救过他的命**"
    },
    {
      "hookId": "H001-陆家恩怨/十三年前火灾",
      "startChapter": 1,
      "type": "剧情",
      "status": "progressing",
      "lastAdvancedChapter": 0,
      "expectedPayoff": "待展开",
      "notes": ""
    },
    {
      "hookId": "SP001-陆家恩怨",
      "startChapter": 0,
      "type": "剧情",
      "status": "open",
      "lastAdvancedChapter": 0,
      "expectedPayoff": "父亲身份重大揭示/新遗物玉牌/坟的概念确立",
      "notes": ""
    },
    {
      "hookId": "SP002-黑虎帮勒索",
      "startChapter": 29,
      "type": "剧情",
      "status": "progressing",
      "lastAdvancedChapter": 0,
      "expectedPayoff": "",
      "notes": ""
    },
    {
      "hookId": "SP006-苏青禾营救",
      "startChapter": 33,
      "type": "剧情",
      "status": "open",
      "lastAdvancedChapter": 44,
      "expectedPayoff": "待处理",
      "notes": "本章激活：闪回提及苏青禾/守脉者印记回应破庙方向/十天整超出约定"
    },
    {
      "hookId": "SP028-不明来人身份",
      "startChapter": 35,
      "type": "剧情",
      "status": "open",
      "lastAdvancedChapter": 35,
      "expectedPayoff": "待展开",
      "notes": "暂无推进"
    },
    {
      "hookId": "SP029-老东家人被囚",
      "startChapter": 33,
      "type": "剧情",
      "status": "progressing",
      "lastAdvancedChapter": 34,
      "expectedPayoff": "**待展开**",
      "notes": "仍被钱进关押？钱进死后状态不明"
    },
    {
      "hookId": "SP030-钱进下一步动向",
      "startChapter": 34,
      "type": "剧情",
      "status": "open",
      "lastAdvancedChapter": 40,
      "expectedPayoff": "待展开",
      "notes": "暂无推进"
    },
    {
      "hookId": "SP039-断手活物",
      "startChapter": 39,
      "type": "悬念",
      "status": "open",
      "lastAdvancedChapter": 39,
      "expectedPayoff": "65章明确交代",
      "notes": "匣内活物/第四只（断手）状态未交代"
    },
    {
      "hookId": "铁匣刻字\"别走\"",
      "startChapter": 0,
      "type": "progressing",
      "status": "open",
      "lastAdvancedChapter": 0,
      "expectedPayoff": "65章新解",
      "notes": ""
    },
    {
      "hookId": "H106-神秘老人身份",
      "startChapter": 32,
      "type": "剧情",
      "status": "open",
      "lastAdvancedChapter": 34,
      "expectedPayoff": "**待展开**",
      "notes": "老人救陆沉三次/知道所有事/身份仍是谜"
    },
    {
      "hookId": "H021-阿纱知道什么",
      "startChapter": 0,
      "type": "progressing",
      "status": "open",
      "lastAdvancedChapter": 0,
      "expectedPayoff": "待展开",
      "notes": "阿纱未收过草茎/但看见过母亲被带走"
    },
    {
      "hookId": "SP021/SP027-令牌追踪",
      "startChapter": 32,
      "type": "剧情",
      "status": "open",
      "lastAdvancedChapter": 34,
      "expectedPayoff": "**待展开**",
      "notes": "老人警告\"令牌别查\"/令牌成对之谜待解"
    },
    {
      "hookId": "\"巢\"是什么",
      "startChapter": 0,
      "type": "open",
      "status": "open",
      "lastAdvancedChapter": 0,
      "expectedPayoff": "65章已完整解释",
      "notes": "65章已完整解释"
    },
    {
      "hookId": "\"别看它们的眼睛\"",
      "startChapter": 0,
      "type": "open",
      "status": "open",
      "lastAdvancedChapter": 0,
      "expectedPayoff": "65章已暗示",
      "notes": "65章已暗示"
    },
    {
      "hookId": "\"不能不要\"",
      "startChapter": 0,
      "type": "open",
      "status": "open",
      "lastAdvancedChapter": 0,
      "expectedPayoff": "65章已完整解释",
      "notes": "65章已完整解释"
    },
    {
      "hookId": "阿纱情感弧线",
      "startChapter": 0,
      "type": "open",
      "status": "open",
      "lastAdvancedChapter": 0,
      "expectedPayoff": "64",
      "notes": "待展开"
    },
    {
      "hookId": "\"有光之地\"",
      "startChapter": 0,
      "type": "open",
      "status": "open",
      "lastAdvancedChapter": 0,
      "expectedPayoff": "待展开",
      "notes": "阿纱母亲知道的地方/三天路程/它们怕光"
    },
    {
      "hookId": "灰白草茎完整关系",
      "startChapter": 0,
      "type": "open",
      "status": "open",
      "lastAdvancedChapter": 0,
      "expectedPayoff": "23",
      "notes": "待展开"
    },
    {
      "hookId": "马七安全",
      "startChapter": 0,
      "type": "open",
      "status": "open",
      "lastAdvancedChapter": 0,
      "expectedPayoff": "-",
      "notes": "待展开"
    },
    {
      "hookId": "SP031-苏青禾的任务",
      "startChapter": 35,
      "type": "剧情",
      "status": "open",
      "lastAdvancedChapter": 35,
      "expectedPayoff": "**已部分解答**",
      "notes": "委托人钱进已确认/苏青禾撒谎保护陆沉已揭露"
    },
    {
      "hookId": "SP032-老人第四次出现",
      "startChapter": 35,
      "type": "剧情",
      "status": "open",
      "lastAdvancedChapter": 36,
      "expectedPayoff": "**已完成**",
      "notes": "老人死亡（掩护陆沉逃离）"
    },
    {
      "hookId": "SP033-十三年前的埋尸",
      "startChapter": 35,
      "type": "剧情",
      "status": "open",
      "lastAdvancedChapter": 35,
      "expectedPayoff": "**已部分解答**",
      "notes": "父母被割喉后拖走埋尸/老人目睹"
    },
    {
      "hookId": "SP001-令牌之谜",
      "startChapter": 1,
      "type": "剧情",
      "status": "progressing",
      "lastAdvancedChapter": 36,
      "expectedPayoff": "待展开",
      "notes": "令牌成对/铜锣山灵脉/钥匙功能"
    },
    {
      "hookId": "SP039-匣内活物之谜",
      "startChapter": 19,
      "type": "悬疑",
      "status": "progressing",
      "lastAdvancedChapter": 43,
      "expectedPayoff": "待揭示",
      "notes": "铁匣子戏份加强，与\"它们\"的关系进一步暗示"
    },
    {
      "hookId": "SP040-它们身份",
      "startChapter": 0,
      "type": "open",
      "status": "open",
      "lastAdvancedChapter": 0,
      "expectedPayoff": "十几只手/灰白鳞片/乌黑指甲",
      "notes": ""
    },
    {
      "hookId": "SP041-山中异常安静",
      "startChapter": 38,
      "type": "剧情",
      "status": "open",
      "lastAdvancedChapter": 40,
      "expectedPayoff": "待展开",
      "notes": "山中安静原因待解释"
    },
    {
      "hookId": "SP042-阿纱的秘密",
      "startChapter": 0,
      "type": "open",
      "status": "open",
      "lastAdvancedChapter": 0,
      "expectedPayoff": "阿纱眼圈红/知道什么",
      "notes": ""
    },
    {
      "hookId": "H021-老人与林子",
      "startChapter": 35,
      "type": "剧情",
      "status": "progressing",
      "lastAdvancedChapter": 36,
      "expectedPayoff": "待展开",
      "notes": "前两天刚从林子出来/伤了元气（身份背景补充）"
    },
    {
      "hookId": "SP034-铜锣山灵脉",
      "startChapter": 36,
      "type": "剧情",
      "status": "open",
      "lastAdvancedChapter": 38,
      "expectedPayoff": "门内探索",
      "notes": "待展开"
    },
    {
      "hookId": "SP035-老人为何取令牌",
      "startChapter": 36,
      "type": "剧情",
      "status": "resolved",
      "lastAdvancedChapter": 38,
      "expectedPayoff": "-",
      "notes": "已解答"
    },
    {
      "hookId": "SP036-钱进追杀动机",
      "startChapter": 36,
      "type": "剧情",
      "status": "progressing",
      "lastAdvancedChapter": 38,
      "expectedPayoff": "追杀队全灭/钱进正面对决",
      "notes": "威胁升级"
    },
    {
      "hookId": "SP018-苏父回归",
      "startChapter": 16,
      "type": "剧情",
      "status": "open",
      "lastAdvancedChapter": 25,
      "expectedPayoff": "待展开",
      "notes": "苏老实已死"
    },
    {
      "hookId": "SP024-魏长的账",
      "startChapter": 0,
      "type": "剧情",
      "status": "open",
      "lastAdvancedChapter": 0,
      "expectedPayoff": "-",
      "notes": ""
    },
    {
      "hookId": "SP029-老东家的人被囚",
      "startChapter": 0,
      "type": "open",
      "status": "open",
      "lastAdvancedChapter": 0,
      "expectedPayoff": "待展开",
      "notes": "暂无推进"
    },
    {
      "hookId": "SP032-老人四次出现",
      "startChapter": 35,
      "type": "剧情",
      "status": "open",
      "lastAdvancedChapter": 35,
      "expectedPayoff": "待展开",
      "notes": "老人身份确认为陆家账房"
    },
    {
      "hookId": "SP033-乱葬岗埋尸",
      "startChapter": 35,
      "type": "剧情",
      "status": "open",
      "lastAdvancedChapter": 35,
      "expectedPayoff": "-",
      "notes": "已确认埋尸真相"
    },
    {
      "hookId": "H021-阿纱状态",
      "startChapter": 37,
      "type": "剧情",
      "status": "open",
      "lastAdvancedChapter": 40,
      "expectedPayoff": "待展开",
      "notes": "阿纱知道通往\"有光之地\"的路/但37章未出场/可能留在村落"
    },
    {
      "hookId": "mystery-铜锣山灵脉相-石室四根蛟龙-浮雕石柱",
      "startChapter": 0,
      "type": "open",
      "status": "open",
      "lastAdvancedChapter": 38,
      "expectedPayoff": "铜锣山灵脉相关",
      "notes": "石室周围多扇石门，虚掩或紧闭，门槛有刮痕，内有何物？"
    },
    {
      "hookId": "mystery-陆家血脉-灵脉关联-陆沉左肩暗红",
      "startChapter": 0,
      "type": "open",
      "status": "open",
      "lastAdvancedChapter": 38,
      "expectedPayoff": "陆家血脉/灵脉关联",
      "notes": "陆沉左肩蛟鳞印记+发热，与灵脉有何关联？"
    },
    {
      "hookId": "plot-铜锣山灵脉-石壁门已打开-父亲遗产在内",
      "startChapter": 0,
      "type": "open",
      "status": "open",
      "lastAdvancedChapter": 38,
      "expectedPayoff": "铜锣山灵脉",
      "notes": "石壁门已打开，父亲遗产（暗道）待探索"
    },
    {
      "hookId": "SP021-荒卫令牌",
      "startChapter": 0,
      "type": "重大推进",
      "status": "open",
      "lastAdvancedChapter": 0,
      "expectedPayoff": "",
      "notes": ""
    },
    {
      "hookId": "SP026-马七的意图",
      "startChapter": 26,
      "type": "剧情",
      "status": "open",
      "lastAdvancedChapter": 40,
      "expectedPayoff": "待展开",
      "notes": "马七向钱进报信（确认）；钱进知道山顶有人守着"
    },
    {
      "hookId": "新钩-守脉者归位含义",
      "startChapter": 42,
      "type": "悬念",
      "status": "progressing",
      "lastAdvancedChapter": 44,
      "expectedPayoff": "含义揭示",
      "notes": "本章深化：守脉者身份确认/守脉者与\"它们\"存在交易关系"
    },
    {
      "hookId": "新钩-暗道内容",
      "startChapter": 39,
      "type": "悬念",
      "status": "progressing",
      "lastAdvancedChapter": 44,
      "expectedPayoff": "暗道探索完成",
      "notes": "本章完成：水下通道→山洞→通往外界/水潭威胁未跟来"
    },
    {
      "hookId": "新钩-灵脉反噬",
      "startChapter": 39,
      "type": "悬念",
      "status": "open",
      "lastAdvancedChapter": 41,
      "expectedPayoff": "待展开",
      "notes": "钱家找了二十年灵脉核心未找到（反噬威力确认）；父亲找到入口但被割喉"
    },
    {
      "hookId": "新钩-马七情报价值",
      "startChapter": 40,
      "type": "悬念",
      "status": "open",
      "lastAdvancedChapter": 41,
      "expectedPayoff": "**待展开**",
      "notes": "**本章新增：黄牙透露马七情报准确/\"钱爷还不信\"/暗示钱进对马七情报有依赖**"
    },
    {
      "hookId": "SP030-钱进的下一步",
      "startChapter": 34,
      "type": "剧情",
      "status": "progressing",
      "lastAdvancedChapter": 44,
      "expectedPayoff": "钱进死亡（64章）",
      "notes": "本章揭示：钱进知道守脉者与\"它们\"的交易/追陆沉另有目的/暗示\"筹码\"问题"
    },
    {
      "hookId": "新钩-守脉者护佑触发",
      "startChapter": 41,
      "type": "悬念",
      "status": "progressing",
      "lastAdvancedChapter": 44,
      "expectedPayoff": "护佑机制完整揭示",
      "notes": "本章确认：鱼引导陆沉逃生/守脉者印记发热回应/灵脉认主"
    },
    {
      "hookId": "新钩-黄牙情报",
      "startChapter": 0,
      "type": "open",
      "status": "open",
      "lastAdvancedChapter": 0,
      "expectedPayoff": "\"守脉者比灵脉核心值钱\"",
      "notes": ""
    },
    {
      "hookId": "新钩-灰白薄膜关联",
      "startChapter": 0,
      "type": "**new**",
      "status": "open",
      "lastAdvancedChapter": 0,
      "expectedPayoff": "**灰白薄膜（骨上）与铁匣絮状物颜色质地相似，与灰白草茎或\"它们\"存在关联**",
      "notes": ""
    },
    {
      "hookId": "mystery-守脉者传承机制揭示-洞室中央悬浮",
      "startChapter": 0,
      "type": "progressing",
      "status": "open",
      "lastAdvancedChapter": 0,
      "expectedPayoff": "洞室中央悬浮淡金色石头在\"呼吸\"，蛟鳞印记与之同频。守脉者与灵脉核心的物理连接机制是什么？血触发了甬道开启，机制待揭示",
      "notes": ""
    },
    {
      "hookId": "mystery-钱进下一步行动揭示",
      "startChapter": 0,
      "type": "open",
      "status": "open",
      "lastAdvancedChapter": 0,
      "expectedPayoff": "钱进追踪至石门外→凿墙→烧穿岩壁→石门被撞开→现在追杀入甬道。下一步：从水潭方向包抄？",
      "notes": ""
    },
    {
      "hookId": "新钩-守脉者坟地",
      "startChapter": 42,
      "type": "悬念",
      "status": "open",
      "lastAdvancedChapter": 43,
      "expectedPayoff": "待揭示",
      "notes": "守脉者坟地的逃生甬道/\"别走\"刻字与铁匣呼应"
    },
    {
      "hookId": "SP006-苏青禾等待",
      "startChapter": 0,
      "type": "**resurfacing**",
      "status": "open",
      "lastAdvancedChapter": 0,
      "expectedPayoff": "**三天期限进行中/陆沉逃亡中想起苏青禾/支线重新激活**",
      "notes": ""
    },
    {
      "hookId": "新钩-死水潭呼吸声",
      "startChapter": 0,
      "type": "**new**",
      "status": "open",
      "lastAdvancedChapter": 0,
      "expectedPayoff": "**水潭另一端传来湿润蠕动的呼吸声，与洞穴深处听到的滴答声和\"它们\"的关系待揭示**",
      "notes": ""
    },
    {
      "hookId": "mystery-守脉者传承机制",
      "startChapter": 0,
      "type": "**进展中**",
      "status": "open",
      "lastAdvancedChapter": 44,
      "expectedPayoff": "待揭示",
      "notes": "蛟鳞印记与守脉者之鱼存在物理连接（额前甲片形状一致/印记全程灼烫）/血液可激活灵脉/但灵脉意志仍是谜"
    },
    {
      "hookId": "H027-骨庙位置",
      "startChapter": 0,
      "type": "progressing",
      "status": "open",
      "lastAdvancedChapter": 0,
      "expectedPayoff": "待展开",
      "notes": "标注骨庙位置"
    },
    {
      "hookId": "SP006-苏青禾支线",
      "startChapter": 0,
      "type": "**警告→临界**",
      "status": "open",
      "lastAdvancedChapter": 25,
      "expectedPayoff": "**65**",
      "notes": "第23章交给孙麻子出城→走城南门乱葬岗方向（假消息）/搜完没人→实际路线不明→65章必须明确处理"
    },
    {
      "hookId": "SP040-钱进遗言",
      "startChapter": 0,
      "type": "progressing",
      "status": "open",
      "lastAdvancedChapter": 0,
      "expectedPayoff": "\"别看它们的眼睛\"/\"巢\"/\"不能不要\"→本章增加\"巢\"与穴居人村落的碎片化联想",
      "notes": ""
    },
    {
      "hookId": "SP042",
      "startChapter": 0,
      "type": "open",
      "status": "open",
      "lastAdvancedChapter": 0,
      "expectedPayoff": "阿纱眼圈红/知道什么",
      "notes": ""
    },
    {
      "hookId": "井底威胁",
      "startChapter": 0,
      "type": "open",
      "status": "open",
      "lastAdvancedChapter": 0,
      "expectedPayoff": "**滴答声/蠕动质感→主角先一步爬出井口→威胁仍在井底深处→是否追出/具体身份→待后续交代**",
      "notes": ""
    },
    {
      "hookId": "SP040-陆沉的抉择",
      "startChapter": 47,
      "type": "**悬念**",
      "status": "progressing",
      "lastAdvancedChapter": 50,
      "expectedPayoff": "**后续章节**",
      "notes": "三个方向→决定先找灵脉核心→青云宗介入→抉择升级"
    },
    {
      "hookId": "SP037-陆沉的娘",
      "startChapter": 0,
      "type": "悬念",
      "status": "open",
      "lastAdvancedChapter": 55,
      "expectedPayoff": "待展开",
      "notes": "本章新增线索：青云宗说\"三年前有个女的把匣子放进裂缝\"/与沈师兄眉心竖纹相关的竖纹刻在铁匣上"
    },
    {
      "hookId": "新钩-守脉者身份",
      "startChapter": 48,
      "type": "**悬念**",
      "status": "progressing",
      "lastAdvancedChapter": 50,
      "expectedPayoff": "**后续章节**",
      "notes": "青云宗不知道守脉者是什么；陆沉掌握关键信息"
    },
    {
      "hookId": "新钩-青云宗追踪",
      "startChapter": 50,
      "type": "**悬念**",
      "status": "open",
      "lastAdvancedChapter": 50,
      "expectedPayoff": "**后续章节**",
      "notes": "青云宗两人追踪陆沉；暂时按兵不动试探"
    },
    {
      "hookId": "新钩-苏青禾状态恶化",
      "startChapter": 50,
      "type": "**悬念**",
      "status": "open",
      "lastAdvancedChapter": 50,
      "expectedPayoff": "**后续章节**",
      "notes": "苏青禾脚踝扭伤+体力透支昏迷；需要照顾"
    },
    {
      "hookId": "新钩-灵脉核心",
      "startChapter": 40,
      "type": "悬念",
      "status": "open",
      "lastAdvancedChapter": 40,
      "expectedPayoff": "待展开",
      "notes": "十三代前被取走的灵脉核心没有消失，被人藏在这座山里/钱家找了二十年"
    },
    {
      "hookId": "SP006-苏青禾安全",
      "startChapter": 33,
      "type": "核心",
      "status": "resolved",
      "lastAdvancedChapter": 49,
      "expectedPayoff": "已完成",
      "notes": "已救出/手腕勒痕/脸上淤青/脚踝扭伤"
    },
    {
      "hookId": "SP040-陆沉抉择",
      "startChapter": 50,
      "type": "抉择",
      "status": "open",
      "lastAdvancedChapter": 50,
      "expectedPayoff": "待展开",
      "notes": "决定不逃避/正面面对灵脉核心和蛞蚀"
    },
    {
      "hookId": "SP041-守脉者传承",
      "startChapter": 48,
      "type": "核心",
      "status": "open",
      "lastAdvancedChapter": 48,
      "expectedPayoff": "待展开",
      "notes": "血亲死亡认主/陆沉已用母亲的命换资格"
    },
    {
      "hookId": "SP042-脉晶",
      "startChapter": 48,
      "type": "核心",
      "status": "open",
      "lastAdvancedChapter": 48,
      "expectedPayoff": "待展开",
      "notes": "脉晶可稳住印记/只能吃一颗/多块待分配"
    },
    {
      "hookId": "SP043-陆焚交易",
      "startChapter": 48,
      "type": "核心",
      "status": "open",
      "lastAdvancedChapter": 48,
      "expectedPayoff": "待展开",
      "notes": "陆焚拿七成/钱进瞒着多拿/但还有账外之事"
    },
    {
      "hookId": "SP044-青云宗目的",
      "startChapter": 50,
      "type": "新开",
      "status": "open",
      "lastAdvancedChapter": 50,
      "expectedPayoff": "待展开",
      "notes": "暂时跟踪试探/等支援/人多势众后动手"
    },
    {
      "hookId": "SP045-青云宗不知守脉者",
      "startChapter": 50,
      "type": "信息优势",
      "status": "open",
      "lastAdvancedChapter": 50,
      "expectedPayoff": "待展开",
      "notes": "青云宗不知道守脉者身份/这是陆沉的优势"
    },
    {
      "hookId": "SP046-钱进之死真相",
      "startChapter": 50,
      "type": "新开→深化",
      "status": "progressing",
      "lastAdvancedChapter": 51,
      "expectedPayoff": "待展开",
      "notes": "钱进为何选择这个时机/蛞蚀为何配合/苏青禾十天期限与三天前的时间线"
    },
    {
      "hookId": "SP047-母亲被送走",
      "startChapter": 48,
      "type": "新开→悬念",
      "status": "open",
      "lastAdvancedChapter": 51,
      "expectedPayoff": "待展开",
      "notes": "母亲被送到了别人手里/不是被保护而是被移交/目的是什么"
    },
    {
      "hookId": "SP048-灵脉蓝光",
      "startChapter": 51,
      "type": "新开",
      "status": "open",
      "lastAdvancedChapter": 51,
      "expectedPayoff": "待展开",
      "notes": "蓝光含义/灵脉等待/蛞蚀也在等待"
    },
    {
      "hookId": "SP049-蛞蚀标记",
      "startChapter": 51,
      "type": "新开",
      "status": "open",
      "lastAdvancedChapter": 51,
      "expectedPayoff": "待展开",
      "notes": "蛞蚀主动标记/钱进死后三天/等待陆沉进入"
    },
    {
      "hookId": "H035-铁匣刻字",
      "startChapter": 56,
      "type": "待展开",
      "status": "open",
      "lastAdvancedChapter": 56,
      "expectedPayoff": "待展开",
      "notes": "刻字含义/警告谁/与穴居人的关系"
    },
    {
      "hookId": "SP039-断手活物-第四只",
      "startChapter": 0,
      "type": "65章明确",
      "status": "open",
      "lastAdvancedChapter": 0,
      "expectedPayoff": "",
      "notes": ""
    },
    {
      "hookId": "SP047-蛟鳞印记回应",
      "startChapter": 0,
      "type": "**52**",
      "status": "open",
      "lastAdvancedChapter": 0,
      "expectedPayoff": "",
      "notes": ""
    },
    {
      "hookId": "SP048-苏青禾留下等待",
      "startChapter": 0,
      "type": "52",
      "status": "open",
      "lastAdvancedChapter": 0,
      "expectedPayoff": "",
      "notes": ""
    },
    {
      "hookId": "SP049-青云宗五人包围",
      "startChapter": 0,
      "type": "52",
      "status": "open",
      "lastAdvancedChapter": 0,
      "expectedPayoff": "",
      "notes": ""
    },
    {
      "hookId": "H035-蛞蚀等待",
      "startChapter": 0,
      "type": "52",
      "status": "open",
      "lastAdvancedChapter": 0,
      "expectedPayoff": "",
      "notes": ""
    },
    {
      "hookId": "新钩-H050-双铁匣之谜",
      "startChapter": 0,
      "type": "52",
      "status": "open",
      "lastAdvancedChapter": 0,
      "expectedPayoff": "",
      "notes": ""
    },
    {
      "hookId": "SP006-苏青禾与孙麻子",
      "startChapter": 11,
      "type": "**极度警告→推进中**",
      "status": "open",
      "lastAdvancedChapter": 53,
      "expectedPayoff": "65章明确状态",
      "notes": "**11章未提及→24章发现灰白布条+双人脚印→推断苏青禾与孙麻子走城东门小路→65章明确状态（活着/安全/遇险）**"
    },
    {
      "hookId": "SP050-核心铁匣",
      "startChapter": 52,
      "type": "重大线索",
      "status": "progressing",
      "lastAdvancedChapter": 55,
      "expectedPayoff": "待展开",
      "notes": "铁匣是母亲遗物；被钱进封存在灵脉核心深处；匣子里有能让蛞蚀发疯的东西；母亲用\"另一种办法\"打开过；铁匣有两套纹路（\"别走\"+竖纹/竖纹与沈师兄眉心竖纹同形）"
    },
    {
      "hookId": "SP051-蛞蚀入核心",
      "startChapter": 52,
      "type": "悬念",
      "status": "progressing",
      "lastAdvancedChapter": 55,
      "expectedPayoff": "待展开",
      "notes": "蛞蚀在核心深处/守在通往深处之路/主动退走/威胁已退（本章交代）"
    },
    {
      "hookId": "SP037-母亲被送走",
      "startChapter": 48,
      "type": "核心悬念",
      "status": "open",
      "lastAdvancedChapter": 52,
      "expectedPayoff": "待展开",
      "notes": "**\"送走\"≠\"藏起来\"/母亲被送到了谁手里/核心岩石台铁匣可能与母亲有关**"
    },
    {
      "hookId": "SP034-核心探索",
      "startChapter": 52,
      "type": "高潮进行",
      "status": "open",
      "lastAdvancedChapter": 52,
      "expectedPayoff": "54-60展开",
      "notes": "**核心探索进行中/发现铁匣+蛞蚀痕迹+对峙**"
    },
    {
      "hookId": "SP052-脚印之谜",
      "startChapter": 53,
      "type": "悬念",
      "status": "open",
      "lastAdvancedChapter": 53,
      "expectedPayoff": "待展开",
      "notes": "女人或小孩脚印/从岩石台延伸至黑暗"
    },
    {
      "hookId": "SP053-铁匣刻痕",
      "startChapter": 0,
      "type": "open",
      "status": "open",
      "lastAdvancedChapter": 0,
      "expectedPayoff": "刻痕眼熟→与守脉者传承/陆家/母亲有关",
      "notes": ""
    },
    {
      "hookId": "伏笔-钱进与蛞蚀",
      "startChapter": 0,
      "type": "open",
      "status": "open",
      "lastAdvancedChapter": 0,
      "expectedPayoff": "钱进能跟蛞蚀说话/两代人中唯二/把自己卖给蛞蚀/血食/走不了",
      "notes": ""
    },
    {
      "hookId": "伏笔-老人身份",
      "startChapter": 0,
      "type": "open",
      "status": "open",
      "lastAdvancedChapter": 0,
      "expectedPayoff": "矿洞幸存者/山脚看坟三十年/\"等你打开匣子就知道了\"/与母亲有救命之恩",
      "notes": ""
    },
    {
      "hookId": "伏笔-母亲遗信",
      "startChapter": 0,
      "type": "open",
      "status": "open",
      "lastAdvancedChapter": 0,
      "expectedPayoff": "信在怀中未拆/老人提到\"另一种办法\"打开匣子/可能与信有关",
      "notes": ""
    },
    {
      "hookId": "SP039-钱进与蛞蚀矛盾",
      "startChapter": 52,
      "type": "悬念",
      "status": "progressing",
      "lastAdvancedChapter": 54,
      "expectedPayoff": "待展开",
      "notes": "钱进能跟蛞蚀说话（两代中只有两个）；把自己卖给蛞蚀；蛞蚀不放血食离开；钱进遗言\"巢\"待解读"
    },
    {
      "hookId": "SP044-青云宗的目的",
      "startChapter": 55,
      "type": "悬念",
      "status": "open",
      "lastAdvancedChapter": 55,
      "expectedPayoff": "待展开",
      "notes": "**青云宗要匣子/能捏住灵脉七寸/守脉者现身**"
    },
    {
      "hookId": "SP045-青云宗对守脉者一无所知",
      "startChapter": 55,
      "type": "悬念",
      "status": "open",
      "lastAdvancedChapter": 55,
      "expectedPayoff": "待展开",
      "notes": "**青云宗不知守脉者身份/只知道\"信物\"/沈师兄亲自出马**"
    },
    {
      "hookId": "H036-阿纱的秘密",
      "startChapter": 53,
      "type": "悬念",
      "status": "open",
      "lastAdvancedChapter": 54,
      "expectedPayoff": "待展开",
      "notes": "阿纱对铁匣有情绪反应/不回答是否收过灰白草茎/威胁退走后留在穴居人村落"
    },
    {
      "hookId": "SP001母亲下落",
      "startChapter": 5,
      "type": "悬念",
      "status": "open",
      "lastAdvancedChapter": 56,
      "expectedPayoff": "待展开",
      "notes": "两年前女人手腕有灰白薄膜（与陆沉记忆中母亲相关？待确认）"
    },
    {
      "hookId": "SP006苏青禾营救",
      "startChapter": 25,
      "type": "支线",
      "status": "progressing",
      "lastAdvancedChapter": 31,
      "expectedPayoff": "**32-33章**",
      "notes": "**第31章完成柳巷东初次侦查；确认两拨人分守（钱进vs老东家）；三天之限重计；窗口期出现**"
    },
    {
      "hookId": "SP039断手活物",
      "startChapter": 0,
      "type": "**open**",
      "status": "open",
      "lastAdvancedChapter": 0,
      "expectedPayoff": "**58章明确：断手仍在匣内，与三只分开，仍有动静→状态待查→逾期状态解除**",
      "notes": ""
    },
    {
      "hookId": "SP050铁匣来源",
      "startChapter": 53,
      "type": "悬念",
      "status": "open",
      "lastAdvancedChapter": 56,
      "expectedPayoff": "待展开",
      "notes": "刻痕符号与钱进刻的一致→**\"巢\"字符号为更早期存在**"
    },
    {
      "hookId": "SP051穴居人与蛞蚀共生",
      "startChapter": 53,
      "type": "悬念",
      "status": "open",
      "lastAdvancedChapter": 56,
      "expectedPayoff": "待展开",
      "notes": "穴居人不怕蛞蚀/蛞蚀不咬他们"
    },
    {
      "hookId": "SP055穴居人村落",
      "startChapter": 56,
      "type": "新开",
      "status": "open",
      "lastAdvancedChapter": 56,
      "expectedPayoff": "待展开",
      "notes": "\"早就知道会有人来\"/阿纱对铁牌有微妙情绪"
    },
    {
      "hookId": "SP056两年前女人",
      "startChapter": 56,
      "type": "悬念",
      "status": "progressing",
      "lastAdvancedChapter": 57,
      "expectedPayoff": "待展开",
      "notes": "**女人给钱进灰白草茎/交代\"不能不要\"/给了铁匣任务/手腕有灰白薄膜/两年前进入山中/\"走了没再回来\"**"
    },
    {
      "hookId": "SP057\"巢\"字含义",
      "startChapter": 56,
      "type": "悬念",
      "status": "progressing",
      "lastAdvancedChapter": 57,
      "expectedPayoff": "待展开",
      "notes": "**钱进解读：那是\"它们\"的巢/符号比穴居人存在更久**"
    },
    {
      "hookId": "SP058山中\"不是人\"的存在",
      "startChapter": 56,
      "type": "悬念",
      "status": "progressing",
      "lastAdvancedChapter": 57,
      "expectedPayoff": "待展开",
      "notes": "**钱进口述：不是蛞蚀/比蛞蚀大得多/在山腰袭击他/\"会死\"警告**"
    },
    {
      "hookId": "SP059阿纱对铁牌的情绪",
      "startChapter": 57,
      "type": "**新伏笔**",
      "status": "open",
      "lastAdvancedChapter": 57,
      "expectedPayoff": "64展开",
      "notes": "**阿纱看到铁牌时皱眉/眼神变化/对两年前女人话题沉默/阿纱手腕无意识动作**"
    },
    {
      "hookId": "伏笔-铁匣活物×3",
      "startChapter": 0,
      "type": "open",
      "status": "open",
      "lastAdvancedChapter": 0,
      "expectedPayoff": "活物特性已知：怕光/体型变化/絮状物是巢穴",
      "notes": ""
    },
    {
      "hookId": "伏笔-穴居人村落真相",
      "startChapter": 0,
      "type": "open",
      "status": "open",
      "lastAdvancedChapter": 0,
      "expectedPayoff": "穴居人\"早就知道会有人来\"/等什么人/与铁匣什么关系",
      "notes": ""
    },
    {
      "hookId": "伏笔-阿纱身份",
      "startChapter": 0,
      "type": "open",
      "status": "open",
      "lastAdvancedChapter": 0,
      "expectedPayoff": "阿纱对铁牌有微妙情绪/知道两年前女人的事",
      "notes": ""
    },
    {
      "hookId": "伏笔-青云宗追杀",
      "startChapter": 0,
      "type": "open",
      "status": "open",
      "lastAdvancedChapter": 0,
      "expectedPayoff": "沈师兄+三人搜索/苏青禾在山上等待/时间窗口紧迫",
      "notes": ""
    },
    {
      "hookId": "伏笔-苏青禾等待",
      "startChapter": 0,
      "type": "open",
      "status": "open",
      "lastAdvancedChapter": 0,
      "expectedPayoff": "山脊灌木丛/脚踝扭伤/灰白薄膜止血/青云宗逼近→时间压力",
      "notes": ""
    },
    {
      "hookId": "伏笔-母亲下落",
      "startChapter": 0,
      "type": "open",
      "status": "open",
      "lastAdvancedChapter": 0,
      "expectedPayoff": "陆沉核心目标",
      "notes": ""
    },
    {
      "hookId": "伏笔-蛟鳞印记",
      "startChapter": 0,
      "type": "open",
      "status": "open",
      "lastAdvancedChapter": 0,
      "expectedPayoff": "剧烈跳动+新增竖纹/疑似锁定标记",
      "notes": ""
    },
    {
      "hookId": "威胁-威胁追踪-远处尖细叫声",
      "startChapter": 0,
      "type": "open",
      "status": "open",
      "lastAdvancedChapter": 0,
      "expectedPayoff": "远处传来尖细声音（像石头刮过竹筒）→非蛞蚀/威胁存在",
      "notes": ""
    },
    {
      "hookId": "威胁-威胁追踪-溶洞深处阴影",
      "startChapter": 0,
      "type": "open",
      "status": "open",
      "lastAdvancedChapter": 0,
      "expectedPayoff": "庞然大物从深处爬向洞口→未解释",
      "notes": ""
    },
    {
      "hookId": "伏笔-\"巢\"字含义",
      "startChapter": 0,
      "type": "open",
      "status": "open",
      "lastAdvancedChapter": 0,
      "expectedPayoff": "钱进临死说\"巢\"/符号比穴居人更古老/\"不是人/不是蛞蚀/会死\"",
      "notes": ""
    },
    {
      "hookId": "伏笔-灰白草茎",
      "startChapter": 0,
      "type": "**推进**",
      "status": "open",
      "lastAdvancedChapter": 58,
      "expectedPayoff": "苏青禾手中草茎与铁匣内絮状物同质→触碰者会被\"带走\"→阿纱警告",
      "notes": ""
    },
    {
      "hookId": "伏笔-\"找人\"闭环",
      "startChapter": 0,
      "type": "open",
      "status": "open",
      "lastAdvancedChapter": 3,
      "expectedPayoff": "**58章阿纱问\"是不是来找人的\"→57章\"很久以前的东西\"→伏笔已闭环/待后续展开**",
      "notes": ""
    },
    {
      "hookId": "伏笔-铁匣刻字\"巢在等\"",
      "startChapter": 0,
      "type": "**已确认**",
      "status": "open",
      "lastAdvancedChapter": 0,
      "expectedPayoff": "原\"别走\"/实为\"巢在等\"→巢的含义待揭示",
      "notes": ""
    },
    {
      "hookId": "伏笔-巢",
      "startChapter": 0,
      "type": "**open**",
      "status": "open",
      "lastAdvancedChapter": 0,
      "expectedPayoff": "巢→阿纱提及→穴居人知道→\"那东西\"所在→母亲可能相关",
      "notes": ""
    },
    {
      "hookId": "伏笔-阿珠与失踪者",
      "startChapter": 0,
      "type": "**open**",
      "status": "open",
      "lastAdvancedChapter": 0,
      "expectedPayoff": "阿珠认识三年前\"收东西\"后失踪的女人→阿珠动机→铁匣交换条件",
      "notes": ""
    },
    {
      "hookId": "伏笔-穴居人洞穴深处来人",
      "startChapter": 0,
      "type": "悬疑",
      "status": "open",
      "lastAdvancedChapter": 0,
      "expectedPayoff": "待展开",
      "notes": "母亲线索待揭示"
    },
    {
      "hookId": "伏笔-城西树林邪门",
      "startChapter": 0,
      "type": "**推进**",
      "status": "open",
      "lastAdvancedChapter": 0,
      "expectedPayoff": "魏长透露父亲叮嘱\"不能进\"/阿珠不往那边走→威胁仍存在",
      "notes": ""
    },
    {
      "hookId": "伏笔-孙麻子失踪",
      "startChapter": 0,
      "type": "**open**",
      "status": "open",
      "lastAdvancedChapter": 0,
      "expectedPayoff": "孙麻子引开追兵后失踪三天→生死未卜→可能的伏笔回收点",
      "notes": ""
    },
    {
      "hookId": "伏笔-母亲与巢",
      "startChapter": 0,
      "type": "**open**",
      "status": "open",
      "lastAdvancedChapter": 0,
      "expectedPayoff": "阿纱\"是不是来找人的\"→钱进\"巢在等\"→母亲可能与巢有关",
      "notes": ""
    },
    {
      "hookId": "新伏笔",
      "startChapter": 26,
      "type": "剧情",
      "status": "open",
      "lastAdvancedChapter": 26,
      "expectedPayoff": "待展开",
      "notes": "**父亲旧人网络**：老头+另一个声音，两人都是父亲旧识→父亲当年在边军有一张关系网？"
    },
    {
      "hookId": "伏笔-钱进遗言",
      "startChapter": 0,
      "type": "open",
      "status": "open",
      "lastAdvancedChapter": 0,
      "expectedPayoff": "\"别看它们眼睛\"/\"巢\"/\"不能不要\"→待65章展开",
      "notes": ""
    },
    {
      "hookId": "伏笔-苏青禾时间线",
      "startChapter": 0,
      "type": "open",
      "status": "open",
      "lastAdvancedChapter": 0,
      "expectedPayoff": "7年前进山vs两年前女人→需后续解释",
      "notes": ""
    },
    {
      "hookId": "伏笔-洞穴深处威胁",
      "startChapter": 0,
      "type": "open",
      "status": "open",
      "lastAdvancedChapter": 0,
      "expectedPayoff": "多张嘴呼吸/湿润蠕动/滴答声→\"它们\"逼近",
      "notes": ""
    },
    {
      "hookId": "H101",
      "startChapter": 0,
      "type": "**新增**",
      "status": "open",
      "lastAdvancedChapter": 0,
      "expectedPayoff": "**第三方监视者：夜间在破庙外踩点/不是孟三的人（孟三往北）/身份不明**",
      "notes": ""
    },
    {
      "hookId": "H102",
      "startChapter": 0,
      "type": "**新增**",
      "status": "open",
      "lastAdvancedChapter": 0,
      "expectedPayoff": "**马七师兄同名：也叫陆沉/与主角关系？父亲与师兄？巧合还是血脉？**",
      "notes": ""
    },
    {
      "hookId": "H001（伏笔-令牌刀痕）",
      "startChapter": 1,
      "type": "悬念",
      "status": "open",
      "lastAdvancedChapter": 29,
      "expectedPayoff": "待展开",
      "notes": "弧度浅，腕力不稳但角度准，一刀切断系带"
    },
    {
      "hookId": "H002（伏笔-十三年前救人者）",
      "startChapter": 1,
      "type": "伏笔",
      "status": "open",
      "lastAdvancedChapter": 32,
      "expectedPayoff": "待展开",
      "notes": "\"很大有力的双手往外推让他跑\"/老人救援"
    },
    {
      "hookId": "H003（伏笔-监视者）",
      "startChapter": 0,
      "type": "progressing",
      "status": "open",
      "lastAdvancedChapter": 0,
      "expectedPayoff": "",
      "notes": ""
    },
    {
      "hookId": "H004（伏笔-空车辙）",
      "startChapter": 34,
      "type": "伏笔",
      "status": "open",
      "lastAdvancedChapter": 34,
      "expectedPayoff": "待展开",
      "notes": "空车辙印"
    },
    {
      "hookId": "H005（伏笔-乱葬岗埋的东西）",
      "startChapter": 0,
      "type": "伏笔",
      "status": "open",
      "lastAdvancedChapter": 0,
      "expectedPayoff": "-",
      "notes": "-"
    },
    {
      "hookId": "H006（伏笔-SU40\"它们\"的身份）",
      "startChapter": 29,
      "type": "伏笔",
      "status": "open",
      "lastAdvancedChapter": 0,
      "expectedPayoff": "",
      "notes": ""
    },
    {
      "hookId": "H007（伏笔-它们怕光）",
      "startChapter": 29,
      "type": "伏笔",
      "status": "open",
      "lastAdvancedChapter": 0,
      "expectedPayoff": "",
      "notes": ""
    },
    {
      "hookId": "H008（伏笔-铁匣刻字\"别走\"）",
      "startChapter": 29,
      "type": "伏笔",
      "status": "open",
      "lastAdvancedChapter": 0,
      "expectedPayoff": "",
      "notes": ""
    },
    {
      "hookId": "H009（伏笔-两年前女人）",
      "startChapter": 29,
      "type": "伏笔",
      "status": "open",
      "lastAdvancedChapter": 0,
      "expectedPayoff": "",
      "notes": ""
    },
    {
      "hookId": "H010（伏笔-阿纱的秘密）",
      "startChapter": 29,
      "type": "伏笔",
      "status": "open",
      "lastAdvancedChapter": 0,
      "expectedPayoff": "",
      "notes": ""
    },
    {
      "hookId": "H011（伏笔-钱进遗言\"巢\"）",
      "startChapter": 29,
      "type": "伏笔",
      "status": "open",
      "lastAdvancedChapter": 0,
      "expectedPayoff": "",
      "notes": ""
    },
    {
      "hookId": "H012（伏笔-洞穴深处阴影）",
      "startChapter": 29,
      "type": "伏笔",
      "status": "open",
      "lastAdvancedChapter": 0,
      "expectedPayoff": "",
      "notes": ""
    },
    {
      "hookId": "H013（伏笔-灰白草茎规则）",
      "startChapter": 29,
      "type": "伏笔",
      "status": "open",
      "lastAdvancedChapter": 0,
      "expectedPayoff": "",
      "notes": ""
    },
    {
      "hookId": "H014（伏笔-钱进\"不能不要\"）",
      "startChapter": 29,
      "type": "伏笔",
      "status": "open",
      "lastAdvancedChapter": 0,
      "expectedPayoff": "",
      "notes": ""
    },
    {
      "hookId": "H015（伏笔-苏青禾时间线矛盾）",
      "startChapter": 29,
      "type": "伏笔",
      "status": "open",
      "lastAdvancedChapter": 0,
      "expectedPayoff": "",
      "notes": ""
    },
    {
      "hookId": "H016（伏笔-阿纱男人死因）",
      "startChapter": 29,
      "type": "伏笔",
      "status": "open",
      "lastAdvancedChapter": 0,
      "expectedPayoff": "",
      "notes": ""
    },
    {
      "hookId": "H017（剧情-洞穴门口异常）",
      "startChapter": 29,
      "type": "剧情",
      "status": "open",
      "lastAdvancedChapter": 0,
      "expectedPayoff": "",
      "notes": ""
    },
    {
      "hookId": "H002（伏笔-铜板来历）",
      "startChapter": 2,
      "type": "悬念",
      "status": "open",
      "lastAdvancedChapter": 2,
      "expectedPayoff": "待展开",
      "notes": "从父亲牌位获得"
    },
    {
      "hookId": "H007-H009",
      "startChapter": 2,
      "type": "悬念",
      "status": "open",
      "lastAdvancedChapter": 2,
      "expectedPayoff": "待展开",
      "notes": "待查"
    },
    {
      "hookId": "H103（伏笔-监视者）",
      "startChapter": 29,
      "type": "悬念",
      "status": "open",
      "lastAdvancedChapter": 30,
      "expectedPayoff": "待展开",
      "notes": "**推进：老人可能就是监视者/往东走/大手老茧**"
    },
    {
      "hookId": "H104（伏笔-令牌刀痕之谜）",
      "startChapter": 29,
      "type": "剧情",
      "status": "open",
      "lastAdvancedChapter": 29,
      "expectedPayoff": "待展开",
      "notes": "有人将此令牌从某人身上取下"
    },
    {
      "hookId": "H105（伏笔-清晨空车）",
      "startChapter": 29,
      "type": "剧情",
      "status": "open",
      "lastAdvancedChapter": 29,
      "expectedPayoff": "待展开",
      "notes": "与监视者有关？"
    },
    {
      "hookId": "H106（伏笔-十三年前救人者身份）",
      "startChapter": 29,
      "type": "剧情",
      "status": "open",
      "lastAdvancedChapter": 30,
      "expectedPayoff": "待展开",
      "notes": "**推进：老人的手很像/同一人的可能性**"
    },
    {
      "hookId": "H107（新增-苏青禾与铁匣子）",
      "startChapter": 30,
      "type": "**剧情**",
      "status": "open",
      "lastAdvancedChapter": 30,
      "expectedPayoff": "待展开",
      "notes": "**\"匣子里的东西是我放的\"/苏青禾知道铁匣子秘密/七年前知情者**"
    },
    {
      "hookId": "H108（新增-钱进遗言解读）",
      "startChapter": 30,
      "type": "**剧情**",
      "status": "open",
      "lastAdvancedChapter": 30,
      "expectedPayoff": "待展开",
      "notes": "**\"巢\"/\"别看它们的眼睛\"/\"不能不要\"/与洞穴深处阴影的关联**"
    },
    {
      "hookId": "H109（新增-老人身份）",
      "startChapter": 30,
      "type": "**剧情**",
      "status": "open",
      "lastAdvancedChapter": 30,
      "expectedPayoff": "待展开",
      "notes": "**可能是监视者/可能是十三年前救人者/目的不明**"
    },
    {
      "hookId": "H110（新增-铁匣子处置）",
      "startChapter": 30,
      "type": "**剧情**",
      "status": "open",
      "lastAdvancedChapter": 30,
      "expectedPayoff": "待展开",
      "notes": "**埋城外/待处理/带部分是信标**"
    },
    {
      "hookId": "H001（十三年前救人者）",
      "startChapter": 1,
      "type": "伏笔",
      "status": "open",
      "lastAdvancedChapter": 31,
      "expectedPayoff": "待展开",
      "notes": "老人与十三年前救人者是否为同一人；那双手的特征（很大/很有力/往外推）vs昨夜老人（杀人熟练/不图回报）；待32章后验证"
    },
    {
      "hookId": "H002（十三年前火灾）",
      "startChapter": 1,
      "type": "伏笔",
      "status": "open",
      "lastAdvancedChapter": 31,
      "expectedPayoff": "待展开",
      "notes": "父亲身份/大火真相/令牌来历/马七师兄关联"
    },
    {
      "hookId": "H103（身份不明的监视者）",
      "startChapter": 28,
      "type": "剧情",
      "status": "open",
      "lastAdvancedChapter": 31,
      "expectedPayoff": "待展开",
      "notes": "夜间在破庙门外停留后离去；城里布鞋+往东走；岔路口站岗→破庙方向；**第31章确认：监视者与老东家关联**；乱葬岗方向相关"
    },
    {
      "hookId": "H104（令牌刀痕）",
      "startChapter": 29,
      "type": "剧情",
      "status": "open",
      "lastAdvancedChapter": 29,
      "expectedPayoff": "待展开",
      "notes": "弧度浅/腕力不稳但角度准/一刀切断系带/有人曾将令牌从某人身上取下"
    },
    {
      "hookId": "H105（清晨空车）",
      "startChapter": 29,
      "type": "剧情",
      "status": "open",
      "lastAdvancedChapter": 29,
      "expectedPayoff": "待展开",
      "notes": "早上有车从岔路口往城里方向/轱辘压得不深（空车）"
    },
    {
      "hookId": "H106（神秘老人登场）",
      "startChapter": 30,
      "type": "mystery",
      "status": "open",
      "lastAdvancedChapter": 30,
      "expectedPayoff": "待展开",
      "notes": "佝偻/老农面孔/动作极快/杀人熟练/不图回报/消失；与十三年前救人者特征部分吻合（H001关联）；**待32章后验证身份**"
    },
    {
      "hookId": "SP001陆家恩怨",
      "startChapter": 1,
      "type": "支线",
      "status": "progressing",
      "lastAdvancedChapter": 31,
      "expectedPayoff": "待展开",
      "notes": "令牌/马七师兄/孟三/老东家/十三年前大火串联中"
    },
    {
      "hookId": "H040（令牌成对）",
      "startChapter": 31,
      "type": "推理",
      "status": "open",
      "lastAdvancedChapter": 31,
      "expectedPayoff": "待展开",
      "notes": "三十七+三十八成对；钱进要一对；十三年前埋的东西"
    },
    {
      "hookId": "H041（两拨人分守）",
      "startChapter": 31,
      "type": "情报",
      "status": "open",
      "lastAdvancedChapter": 31,
      "expectedPayoff": "待展开",
      "notes": "钱进的人守柳巷东（干活人布鞋）；老东家的人监视岔路口（城里布鞋）；两拨人不是一起；窗口期来源"
    },
    {
      "hookId": "H001（令牌之谜）",
      "startChapter": 1,
      "type": "悬念",
      "status": "open",
      "lastAdvancedChapter": 32,
      "expectedPayoff": "待展开",
      "notes": "三十七号令牌/刀痕/成对/十三年前遗物"
    },
    {
      "hookId": "H106（神秘老人）",
      "startChapter": 30,
      "type": "悬念",
      "status": "open",
      "lastAdvancedChapter": 32,
      "expectedPayoff": "待展开",
      "notes": "佝偻老农面孔/动作极快/杀人熟练/救人不图钱名"
    },
    {
      "hookId": "SP006（苏青禾营救）",
      "startChapter": 31,
      "type": "剧情",
      "status": "open",
      "lastAdvancedChapter": 32,
      "expectedPayoff": "**第33章推进**",
      "notes": "棚户区空虚/井边可疑人影/窗口已开/今晚行动"
    },
    {
      "hookId": "SP027（令牌刀痕）",
      "startChapter": 29,
      "type": "剧情",
      "status": "open",
      "lastAdvancedChapter": 32,
      "expectedPayoff": "待展开",
      "notes": "系带被割断/腕力不稳/角度准/从背后下手"
    },
    {
      "hookId": "SU40（\"它们\"的身份）",
      "startChapter": 65,
      "type": "悬念",
      "status": "open",
      "lastAdvancedChapter": 0,
      "expectedPayoff": "待展开",
      "notes": ""
    },
    {
      "hookId": "H106-老人身份",
      "startChapter": 29,
      "type": "剧情",
      "status": "progressing",
      "lastAdvancedChapter": 33,
      "expectedPayoff": "待展开",
      "notes": "**33章推进**：老人第三次出现（沟渠跟踪/指路/\"令牌的事别查了\"/救陆沉逃离）；陆沉已接受帮助但未追问；**34章新增**：窑外不明脚步声→老人可能在暗中跟随？"
    },
    {
      "hookId": "H001-SP001陆家恩怨",
      "startChapter": 1,
      "type": "剧情",
      "status": "progressing",
      "lastAdvancedChapter": 33,
      "expectedPayoff": "待展开",
      "notes": "十三年前大火/父亲身份/马七师兄同名/令牌刀痕/老人与救人者/令牌与苏青禾娘之死关联"
    },
    {
      "hookId": "SP027苏青禾身世",
      "startChapter": 0,
      "type": "剧情",
      "status": "open",
      "lastAdvancedChapter": 36,
      "expectedPayoff": "**待展开**",
      "notes": "苏青禾母亲是苏婉姐姐/被带进灵脉"
    },
    {
      "hookId": "H003-监视者",
      "startChapter": 29,
      "type": "剧情",
      "status": "progressing",
      "lastAdvancedChapter": 33,
      "expectedPayoff": "待展开",
      "notes": "城里布鞋/千层底厚胶皮鞋/岔路口空瓦罐声/窑外不明脚步声→是老人还是另有其人？"
    },
    {
      "hookId": "SP021令牌之谜",
      "startChapter": 29,
      "type": "剧情",
      "status": "progressing",
      "lastAdvancedChapter": 33,
      "expectedPayoff": "待展开",
      "notes": "令牌被老东家的人持有/给过老东家/钱进审讯/老东家救过囚犯命/囚犯宁死不说真正令牌在哪/\"令牌的事别查了\"警告"
    },
    {
      "hookId": "H108-窑外目光",
      "startChapter": 34,
      "type": "悬念",
      "status": "open",
      "lastAdvancedChapter": 34,
      "expectedPayoff": "待展开",
      "notes": "**34章新增**：窑外不明脚步声远去后，黑暗中似乎有目光注视砖窑；陆沉未回头确认"
    },
    {
      "hookId": "H109-苏青禾梦呓",
      "startChapter": 34,
      "type": "悬念",
      "status": "open",
      "lastAdvancedChapter": 34,
      "expectedPayoff": "待展开",
      "notes": "**34章新增**：苏青禾梦中呢喃\"别走\"，与铁匣子刻字\"别走\"呼应→梦中回忆还是预感？"
    },
    {
      "hookId": "H110-追问苏青禾之母",
      "startChapter": 33,
      "type": "剧情",
      "status": "open",
      "lastAdvancedChapter": 33,
      "expectedPayoff": "待展开",
      "notes": "**33章新增**：有人在审讯苏青禾时反复追问其母名字/\"你娘叫什么名字\"/每次盯着她的脸看→在确认什么？"
    },
    {
      "hookId": "H111-苏老实\"害死\"",
      "startChapter": 33,
      "type": "剧情",
      "status": "open",
      "lastAdvancedChapter": 33,
      "expectedPayoff": "待展开",
      "notes": "**33章新增**：苏老实说\"那块牌子害死了她\"→她是谁？苏青禾的娘？牌子与大火/钱进/老东家有什么关系？"
    },
    {
      "hookId": "SP040（\"它们\"的身份）",
      "startChapter": 65,
      "type": "悬念",
      "status": "open",
      "lastAdvancedChapter": 0,
      "expectedPayoff": "待展开",
      "notes": ""
    },
    {
      "hookId": "新增-H001-苏青禾娘可能还活着",
      "startChapter": 65,
      "type": "剧情",
      "status": "open",
      "lastAdvancedChapter": 0,
      "expectedPayoff": "待展开",
      "notes": ""
    },
    {
      "hookId": "新增-H002-阿纱之母知情",
      "startChapter": 65,
      "type": "剧情",
      "status": "open",
      "lastAdvancedChapter": 0,
      "expectedPayoff": "待展开",
      "notes": ""
    },
    {
      "hookId": "新增-H003-青云宗动向",
      "startChapter": 65,
      "type": "剧情",
      "status": "open",
      "lastAdvancedChapter": 0,
      "expectedPayoff": "待展开",
      "notes": ""
    },
    {
      "hookId": "H001-令牌成对之谜",
      "startChapter": 0,
      "type": "-",
      "status": "open",
      "lastAdvancedChapter": 36,
      "expectedPayoff": "**待展开**",
      "notes": "三十七号开门/三十八号封印/顺序已揭示"
    },
    {
      "hookId": "H001-陆家恩怨",
      "startChapter": 0,
      "type": "-",
      "status": "open",
      "lastAdvancedChapter": 36,
      "expectedPayoff": "**待展开**",
      "notes": "钱进确认凶手/老人报恩/母亲刻字待找"
    },
    {
      "hookId": "mystery-铜锣山灵脉相关",
      "startChapter": 0,
      "type": "推进",
      "status": "open",
      "lastAdvancedChapter": 0,
      "expectedPayoff": "",
      "notes": ""
    },
    {
      "hookId": "mystery-陆家血脉-灵脉关联",
      "startChapter": 0,
      "type": "推进",
      "status": "open",
      "lastAdvancedChapter": 0,
      "expectedPayoff": "",
      "notes": ""
    },
    {
      "hookId": "plot-铜锣山灵脉-石壁门已打开",
      "startChapter": 0,
      "type": "推进",
      "status": "open",
      "lastAdvancedChapter": 0,
      "expectedPayoff": "",
      "notes": ""
    },
    {
      "hookId": "H004-空车辙",
      "startChapter": 0,
      "type": "悬置",
      "status": "open",
      "lastAdvancedChapter": 0,
      "expectedPayoff": "",
      "notes": ""
    },
    {
      "hookId": "新钩-马七背叛",
      "startChapter": 40,
      "type": "悬念",
      "status": "open",
      "lastAdvancedChapter": 40,
      "expectedPayoff": "待展开",
      "notes": "马七向钱进报信/知道父亲发现入口/马七往破庙方向去了/破庙曾着火"
    },
    {
      "hookId": "新钩-破庙之火",
      "startChapter": 40,
      "type": "悬念",
      "status": "open",
      "lastAdvancedChapter": 40,
      "expectedPayoff": "待展开",
      "notes": "父亲出事后第二天破庙着火/有人故意毁掉什么/与苏青禾有何关联"
    },
    {
      "hookId": "新钩-守脉者感应能力",
      "startChapter": 40,
      "type": "悬念",
      "status": "open",
      "lastAdvancedChapter": 40,
      "expectedPayoff": "待展开",
      "notes": "可感应山顶/地底入口方向/感应能力与灵脉相连"
    },
    {
      "hookId": "H005-乱葬岗埋的东西",
      "startChapter": 5,
      "type": "伏笔",
      "status": "open",
      "lastAdvancedChapter": 5,
      "expectedPayoff": "待揭示",
      "notes": "父亲遗物相关"
    },
    {
      "hookId": "SP039-铁匣子活物",
      "startChapter": 0,
      "type": "伏笔",
      "status": "open",
      "lastAdvancedChapter": 0,
      "expectedPayoff": "匣内活物×4已死/絮状物巢穴/与灵脉石头同质性确认",
      "notes": ""
    },
    {
      "hookId": "新钩-守脉者印记预警",
      "startChapter": 0,
      "type": "悬念",
      "status": "open",
      "lastAdvancedChapter": 0,
      "expectedPayoff": "与第41章灵脉护佑呼应/危险信号",
      "notes": ""
    },
    {
      "hookId": "新钩-灵脉坟",
      "startChapter": 0,
      "type": "悬念",
      "status": "open",
      "lastAdvancedChapter": 0,
      "expectedPayoff": "SP001核心揭示",
      "notes": ""
    },
    {
      "hookId": "新钩-陆焚玉牌",
      "startChapter": 0,
      "type": "悬念",
      "status": "open",
      "lastAdvancedChapter": 0,
      "expectedPayoff": "父亲相关遗物/情感锚点",
      "notes": ""
    },
    {
      "hookId": "mystery-守脉者传承机制揭示",
      "startChapter": 42,
      "type": "mystery",
      "status": "progressing",
      "lastAdvancedChapter": 43,
      "expectedPayoff": "守脉者传承机制揭示",
      "notes": "本章确认：鱼眼认出蛟鳞印记/灵脉主动引路/守脉者血被灵脉承认"
    },
    {
      "hookId": "SP039-铁匣活物曾试图爬向苏青禾",
      "startChapter": 55,
      "type": "剧情",
      "status": "progressing",
      "lastAdvancedChapter": 55,
      "expectedPayoff": "待揭示",
      "notes": "断手持续在匣壁上爬动→被阻止"
    },
    {
      "hookId": "新钩-苏青禾的最后期限",
      "startChapter": 47,
      "type": "**悬念**",
      "status": "open",
      "lastAdvancedChapter": 48,
      "expectedPayoff": "**下一章**",
      "notes": "**三天期限，剩余约1.5天；钱进在第48章提及；陆沉决定返回破庙确认苏青禾安全→钱进同行→悬念保持活跃**"
    },
    {
      "hookId": "新钩-蛞蝓的来历",
      "startChapter": 47,
      "type": "**悬念**",
      "status": "open",
      "lastAdvancedChapter": 47,
      "expectedPayoff": "**47**",
      "notes": "**灵脉养出来的/脉气凝成/非人非妖/吃龙脉死后的腐肉（尸气）/不会主动伤人/踩到领域才会被赶**"
    },
    {
      "hookId": "新钩-钱进与蛞蝓的关系",
      "startChapter": 47,
      "type": "**悬念**",
      "status": "open",
      "lastAdvancedChapter": 47,
      "expectedPayoff": "**待展开**",
      "notes": "**钱进能跟蛞蝓说话；蛞蝓放他走；暗示钱进与守脉者/灵脉有更深的关联**"
    },
    {
      "hookId": "新钩-陆焚遗书",
      "startChapter": 46,
      "type": "**揭露**",
      "status": "open",
      "lastAdvancedChapter": 48,
      "expectedPayoff": "-",
      "notes": "**第一封：守脉者身份/娘在镇子里等你；第二封：追杀真相/脉晶位置/母亲去向**"
    },
    {
      "hookId": "新钩-娘在山脚的镇子里等你",
      "startChapter": 46,
      "type": "**悬念**",
      "status": "open",
      "lastAdvancedChapter": 48,
      "expectedPayoff": "**待展开**",
      "notes": "**母亲被送走/去了很远的地方/远到钱进的人找不到→重大伏笔待揭示**"
    },
    {
      "hookId": "新钩-陆焚的另一封信",
      "startChapter": 46,
      "type": "**悬念**",
      "status": "open",
      "lastAdvancedChapter": 48,
      "expectedPayoff": "-",
      "notes": "**第二封信完整揭露追杀真相**"
    },
    {
      "hookId": "新钩-守脉者之眼",
      "startChapter": 46,
      "type": "**悬念**",
      "status": "open",
      "lastAdvancedChapter": 46,
      "expectedPayoff": "**待展开**",
      "notes": "**指路/确认陆焚已死**"
    },
    {
      "hookId": "新钩-守脉者的路只能一个人走",
      "startChapter": 46,
      "type": "**伏笔**",
      "status": "open",
      "lastAdvancedChapter": 46,
      "expectedPayoff": "**待展开**",
      "notes": "**守脉者传承/钱进不能进入核心区域**"
    },
    {
      "hookId": "新钩-山洞岔路",
      "startChapter": 46,
      "type": "**悬念**",
      "status": "open",
      "lastAdvancedChapter": 46,
      "expectedPayoff": "**待展开**",
      "notes": "**通往灵脉核心**"
    },
    {
      "hookId": "新钩-灵脉核心位置",
      "startChapter": 46,
      "type": "**悬念**",
      "status": "open",
      "lastAdvancedChapter": 48,
      "expectedPayoff": "**待展开**",
      "notes": "**位置标在遗书背面/需要陆沉自己前往**"
    },
    {
      "hookId": "新钩-陆沉vs钱进最终对决",
      "startChapter": 45,
      "type": "**悬念**",
      "status": "open",
      "lastAdvancedChapter": 48,
      "expectedPayoff": "-",
      "notes": "**账清各走各路/钱进不再追杀/三百两银子账待解决**"
    },
    {
      "hookId": "新钩-钱进当年被放过一命",
      "startChapter": 45,
      "type": "**悬念**",
      "status": "open",
      "lastAdvancedChapter": 46,
      "expectedPayoff": "-",
      "notes": "**遗书确认：陆焚当年放过钱进/追杀是还债的方式**"
    }
  ]
}