{
  "chapter": 167,
  "facts": [
    {
      "subject": "protagonist",
      "predicate": "当前位置",
      "object": "聚居点石屋→准备出发前往城东",
      "validFromChapter": 167,
      "validUntilChapter": null,
      "sourceChapter": 167
    },
    {
      "subject": "protagonist",
      "predicate": "主角状态",
      "object": "金痕蛰伏/玉坠持续降温（守夜者三天期限进行中）/决心坚定/决断形成/情感觉醒持续/行动方案确立",
      "validFromChapter": 167,
      "validUntilChapter": null,
      "sourceChapter": 167
    },
    {
      "subject": "protagonist",
      "predicate": "当前目标",
      "object": "下午前往城东探查/查清正本清源祭坛位置/验证令牌可用性/阻止正本清源打开通道/三天期限第一天紧迫",
      "validFromChapter": 167,
      "validUntilChapter": null,
      "sourceChapter": 167
    },
    {
      "subject": "protagonist",
      "predicate": "当前限制",
      "object": "寿元不足两年（持续消耗中）/隐息符用尽/神识消耗/体力精力部分恢复/三天期限（春分之前）/玉坠降温加速",
      "validFromChapter": 167,
      "validUntilChapter": null,
      "sourceChapter": 167
    },
    {
      "subject": "protagonist",
      "predicate": "当前敌我",
      "object": "苏婉儿(同行者/三源同源者/核心盟友/被盯上/留守)/赵猛(同行者/誓言同行/被盯上/同行)/青鸾(同行者/留守聚居点/被盯上)",
      "validFromChapter": 167,
      "validUntilChapter": null,
      "sourceChapter": 167
    },
    {
      "subject": "protagonist",
      "predicate": "当前冲突",
      "object": "正本清源撕裂封印（井是通道碎片/祭品撑开裂缝/三十二份祭品/春分前完成/井口是障眼法/祭坛在别处）vs 三源血脉修复封印（寿元不足两年/金痕持续消耗/令牌可用性待验证）",
      "validFromChapter": 167,
      "validUntilChapter": null,
      "sourceChapter": 167
    }
  ]
}