{"nodes": [{"id": "url_d", "label": "url.d.ts", "file_type": "code", "source_file": "E:\\workspace\\inkos\\packages\\cli\\node_modules\\@actalk\\inkos-studio\\node_modules\\@types\\node\\url.d.ts", "source_location": "L1"}, {"id": "url_d_url", "label": "URL", "file_type": "code", "source_file": "E:\\workspace\\inkos\\packages\\cli\\node_modules\\@actalk\\inkos-studio\\node_modules\\@types\\node\\url.d.ts", "source_location": "L409"}, {"id": "url_d_urlsearchparams", "label": "URLSearchParams", "file_type": "code", "source_file": "E:\\workspace\\inkos\\packages\\cli\\node_modules\\@actalk\\inkos-studio\\node_modules\\@types\\node\\url.d.ts", "source_location": "L819"}], "edges": [{"source": "url_d", "target": "node_buffer", "relation": "imports_from", "confidence": "EXTRACTED", "source_file": "E:\\workspace\\inkos\\packages\\cli\\node_modules\\@actalk\\inkos-studio\\node_modules\\@types\\node\\url.d.ts", "source_location": "L11", "weight": 1.0}, {"source": "url_d", "target": "node_http", "relation": "imports_from", "confidence": "EXTRACTED", "source_file": "E:\\workspace\\inkos\\packages\\cli\\node_modules\\@actalk\\inkos-studio\\node_modules\\@types\\node\\url.d.ts", "source_location": "L12", "weight": 1.0}, {"source": "url_d", "target": "node_querystring", "relation": "imports_from", "confidence": "EXTRACTED", "source_file": "E:\\workspace\\inkos\\packages\\cli\\node_modules\\@actalk\\inkos-studio\\node_modules\\@types\\node\\url.d.ts", "source_location": "L13", "weight": 1.0}, {"source": "url_d", "target": "url_d_url", "relation": "contains", "confidence": "EXTRACTED", "source_file": "E:\\workspace\\inkos\\packages\\cli\\node_modules\\@actalk\\inkos-studio\\node_modules\\@types\\node\\url.d.ts", "source_location": "L409", "weight": 1.0}, {"source": "url_d", "target": "url_d_urlsearchparams", "relation": "contains", "confidence": "EXTRACTED", "source_file": "E:\\workspace\\inkos\\packages\\cli\\node_modules\\@actalk\\inkos-studio\\node_modules\\@types\\node\\url.d.ts", "source_location": "L819", "weight": 1.0}, {"source": "url_d", "target": "url", "relation": "imports_from", "confidence": "EXTRACTED", "source_file": "E:\\workspace\\inkos\\packages\\cli\\node_modules\\@actalk\\inkos-studio\\node_modules\\@types\\node\\url.d.ts", "source_location": "L952", "weight": 1.0}]}