{"nodes": [{"id": "composer_test", "label": "composer.test.ts", "file_type": "code", "source_file": "E:\\workspace\\inkos\\packages\\core\\src\\__tests__\\composer.test.ts", "source_location": "L1"}], "edges": [{"source": "composer_test", "target": "vitest", "relation": "imports_from", "confidence": "EXTRACTED", "source_file": "E:\\workspace\\inkos\\packages\\core\\src\\__tests__\\composer.test.ts", "source_location": "L1", "weight": 1.0}, {"source": "composer_test", "target": "node_module", "relation": "imports_from", "confidence": "EXTRACTED", "source_file": "E:\\workspace\\inkos\\packages\\core\\src\\__tests__\\composer.test.ts", "source_location": "L2", "weight": 1.0}, {"source": "composer_test", "target": "promises", "relation": "imports_from", "confidence": "EXTRACTED", "source_file": "E:\\workspace\\inkos\\packages\\core\\src\\__tests__\\composer.test.ts", "source_location": "L3", "weight": 1.0}, {"source": "composer_test", "target": "node_os", "relation": "imports_from", "confidence": "EXTRACTED", "source_file": "E:\\workspace\\inkos\\packages\\core\\src\\__tests__\\composer.test.ts", "source_location": "L4", "weight": 1.0}, {"source": "composer_test", "target": "node_path", "relation": "imports_from", "confidence": "EXTRACTED", "source_file": "E:\\workspace\\inkos\\packages\\core\\src\\__tests__\\composer.test.ts", "source_location": "L5", "weight": 1.0}, {"source": "composer_test", "target": "book_js", "relation": "imports_from", "confidence": "EXTRACTED", "source_file": "E:\\workspace\\inkos\\packages\\core\\src\\__tests__\\composer.test.ts", "source_location": "L6", "weight": 1.0}, {"source": "composer_test", "target": "planner_js", "relation": "imports_from", "confidence": "EXTRACTED", "source_file": "E:\\workspace\\inkos\\packages\\core\\src\\__tests__\\composer.test.ts", "source_location": "L7", "weight": 1.0}, {"source": "composer_test", "target": "composer_js", "relation": "imports_from", "confidence": "EXTRACTED", "source_file": "E:\\workspace\\inkos\\packages\\core\\src\\__tests__\\composer.test.ts", "source_location": "L8", "weight": 1.0}]}