{"nodes": [{"id": "local_fix_patches_test", "label": "local-fix-patches.test.ts", "file_type": "code", "source_file": "E:\\workspace\\inkos\\packages\\core\\src\\__tests__\\local-fix-patches.test.ts", "source_location": "L1"}], "edges": [{"source": "local_fix_patches_test", "target": "vitest", "relation": "imports_from", "confidence": "EXTRACTED", "source_file": "E:\\workspace\\inkos\\packages\\core\\src\\__tests__\\local-fix-patches.test.ts", "source_location": "L1", "weight": 1.0}, {"source": "local_fix_patches_test", "target": "local_fix_patches_js", "relation": "imports_from", "confidence": "EXTRACTED", "source_file": "E:\\workspace\\inkos\\packages\\core\\src\\__tests__\\local-fix-patches.test.ts", "source_location": "L2", "weight": 1.0}]}