{"nodes": [{"id": "stylemanager", "label": "StyleManager.tsx", "file_type": "code", "source_file": "E:\\workspace\\inkos\\packages\\studio\\src\\pages\\StyleManager.tsx", "source_location": "L1"}, {"id": "stylemanager_buildstylestatusnotice", "label": "buildStyleStatusNotice()", "file_type": "code", "source_file": "E:\\workspace\\inkos\\packages\\studio\\src\\pages\\StyleManager.tsx", "source_location": "L30"}, {"id": "stylemanager_handleanalyze", "label": "handleAnalyze()", "file_type": "code", "source_file": "E:\\workspace\\inkos\\packages\\studio\\src\\pages\\StyleManager.tsx", "source_location": "L54"}, {"id": "stylemanager_handleimport", "label": "handleImport()", "file_type": "code", "source_file": "E:\\workspace\\inkos\\packages\\studio\\src\\pages\\StyleManager.tsx", "source_location": "L72"}], "edges": [{"source": "stylemanager", "target": "react", "relation": "imports_from", "confidence": "EXTRACTED", "source_file": "E:\\workspace\\inkos\\packages\\studio\\src\\pages\\StyleManager.tsx", "source_location": "L1", "weight": 1.0}, {"source": "stylemanager", "target": "use_api", "relation": "imports_from", "confidence": "EXTRACTED", "source_file": "E:\\workspace\\inkos\\packages\\studio\\src\\pages\\StyleManager.tsx", "source_location": "L2", "weight": 1.0}, {"source": "stylemanager", "target": "use_theme", "relation": "imports_from", "confidence": "EXTRACTED", "source_file": "E:\\workspace\\inkos\\packages\\studio\\src\\pages\\StyleManager.tsx", "source_location": "L3", "weight": 1.0}, {"source": "stylemanager", "target": "use_i18n", "relation": "imports_from", "confidence": "EXTRACTED", "source_file": "E:\\workspace\\inkos\\packages\\studio\\src\\pages\\StyleManager.tsx", "source_location": "L4", "weight": 1.0}, {"source": "stylemanager", "target": "use_colors", "relation": "imports_from", "confidence": "EXTRACTED", "source_file": "E:\\workspace\\inkos\\packages\\studio\\src\\pages\\StyleManager.tsx", "source_location": "L5", "weight": 1.0}, {"source": "stylemanager", "target": "lucide_react", "relation": "imports_from", "confidence": "EXTRACTED", "source_file": "E:\\workspace\\inkos\\packages\\studio\\src\\pages\\StyleManager.tsx", "source_location": "L6", "weight": 1.0}, {"source": "stylemanager", "target": "stylemanager_buildstylestatusnotice", "relation": "contains", "confidence": "EXTRACTED", "source_file": "E:\\workspace\\inkos\\packages\\studio\\src\\pages\\StyleManager.tsx", "source_location": "L30", "weight": 1.0}, {"source": "stylemanager", "target": "stylemanager_handleanalyze", "relation": "contains", "confidence": "EXTRACTED", "source_file": "E:\\workspace\\inkos\\packages\\studio\\src\\pages\\StyleManager.tsx", "source_location": "L54", "weight": 1.0}, {"source": "stylemanager", "target": "stylemanager_handleimport", "relation": "contains", "confidence": "EXTRACTED", "source_file": "E:\\workspace\\inkos\\packages\\studio\\src\\pages\\StyleManager.tsx", "source_location": "L72", "weight": 1.0}]}