{
  "chapter": 65,
  "facts": [
    {
      "subject": "protagonist",
      "predicate": "当前位置",
      "object": "**岭南城外→落梅村方向（城外三里破庙出发+往东十里）**",
      "validFromChapter": 65,
      "validUntilChapter": null,
      "sourceChapter": 65
    },
    {
      "subject": "protagonist",
      "predicate": "主角状态",
      "object": "身体虚弱但稳定；凤凰玉佩在手（刻\"念奴\"+两块合璧已展示）；\"苏氏\"玉佩在苏青手中；空间泉水恢复中；空间物资（压缩饼干/花生饼/干果/花生糖/药酒/消炎药粉）；**已成功撤离岭南城流放营**；苏青伤势恶化（伤口又裂了+血渗透包扎布条）+但能撑住+持有\"苏氏\"玉佩+今夜一起撤离；获得铜牌（落梅村信物+背面刻莲花符号）；获得老夫人纸笺（出城路线+哨卡位置+落梅村方向+铁匠铺是假的+真正接应在城东药王街尾）；**获得老妪包袱（干粮+水）**",
      "validFromChapter": 65,
      "validUntilChapter": null,
      "sourceChapter": 65
    },
    {
      "subject": "protagonist",
      "predicate": "当前目标",
      "object": "**往东十里落梅村**；**天亮前出岭南府地界**；**带苏青一起撤离**；**保管好铜牌和两块玉佩**；**找到\"苏家的根\"**",
      "validFromChapter": 65,
      "validUntilChapter": null,
      "sourceChapter": 65
    },
    {
      "subject": "protagonist",
      "predicate": "当前限制",
      "object": "身体虚弱未完全恢复；**苏青伤口又裂+需要休息但不能停**；**郑老卒封堵地道后留在地道深处**；**周砚的人发现铁匠铺暴露后会来找接应点**；**流放营里有内鬼（盯着苏晚清）**；**海捕文书通缉苏念奴（母亲名字泄露）**；**城中有火光搜索向城东方向蔓延**；**苏青三五日内不要走动但被迫撤离**",
      "validFromChapter": 65,
      "validUntilChapter": null,
      "sourceChapter": 65
    },
    {
      "subject": "protagonist",
      "predicate": "当前敌我",
      "object": "老李（彻底稳固+执行盯人任务）；翠竹（忠诚执行）；方德正（深度合作+情报持续分享）；周管事（暗处跟随）；吴管事（流放营管事，已打点）；陈掌柜（被迫站队成功+危机中）；沈蓉（正面交锋+敌对升级）；苏青（盟友确立+持有\"苏氏\"玉佩+伤势恶化但能撑住+今夜一起撤离）；**济世堂（被迫站队+背后是镇国公府+老夫人是苏家嫡女+总号被封+紧急危机）**；镇国公府（持续追杀）；周砚（**按察使司佥事+查控神毒药案+调动按察使司发文+三日后会来搜人+背后有一整张网**）；**郑老卒（与孙押役有联系+与城西有关联+十五年前欠苏念奴一条命+今夜还命+杀铁匠铺的人引开敌人+封堵地道后留在深处引开追兵）**；老夫人（**苏家嫡女+嫁进镇国公府+保管\"苏氏\"玉佩+布局十五年保护苏晚清+给了纸笺**）；**孙押役（死亡！被灭口）**；**流放营里的未知敌人（杀孙押役灭口+盯着苏晚清）**；**老妪（落梅村方向接应人）**",
      "validFromChapter": 65,
      "validUntilChapter": null,
      "sourceChapter": 65
    },
    {
      "subject": "protagonist",
      "predicate": "当前冲突",
      "object": "**孙押役被灭口（流放营里有人杀了他）**；**\"周砚是狼\"纸条（孙押役死前留下）**；**海捕文书通缉苏念奴（母亲名字泄露+有人泄密）**；**周砚三日后搜人（紧急威胁）**；**流放营里有内鬼（盯着苏晚清）**；**济世堂总号被封（紧急危机）**；**控神毒药案真相揭露（苏家是南疆医族+控神毒药是苏家炼的+朝廷灭口+苏家满门没了+只有老夫人和苏青母亲活下来）**；**老夫人身份揭露（苏家嫡女+嫁进镇国公府）**；**济世堂与镇国公府关系揭露**；凤凰玉佩两块（\"念奴\"+ \"苏氏\"+合璧是钥匙）；**铜牌验证成功（接应点确认+莲花符号吻合）**；**郑老卒身份揭露（欠苏念奴一条命+十五年前）**；**铁匠铺的人是郑老卒杀的（三日前引开追兵）**；**地道撤离成功（郑老卒封堵身后路）**；**\"苏家的根\"在落梅村（即将抵达）**",
      "validFromChapter": 65,
      "validUntilChapter": null,
      "sourceChapter": 65
    }
  ]
}